{
  "verses": [
    {
      "id": 3504,
      "verse_number": 1,
      "verse_key": "32:1",
      "hizb_number": 42,
      "rub_el_hizb_number": 165,
      "ruku_number": 360,
      "manzil_number": 5,
      "sajdah_number": null,
      "text_uthmani": " الٓمٓ",
      "text_uthmani_tajweed": "ا<tajweed class=madda_necessary>لٓ</tajweed><tajweed class=madda_necessary>مٓ</tajweed> <span class=end>١</span>",
      "page_number": 415,
      "juz_number": 21,
      "audio": {
        "url": "Alafasy/mp3/032001.mp3",
        "segments": [
          [
            0,
            1,
            100,
            7450
          ]
        ]
      },
      "translations": [
        {
          "id": 661447,
          "resource_id": 101,
          "text": "Алиф, Лом, Мим."
        }
      ],
      "audio_url": "https://audio.quran.com/reciters/7/Alafasy/mp3/032001.mp3"
    },
    {
      "id": 3505,
      "verse_number": 2,
      "verse_key": "32:2",
      "hizb_number": 42,
      "rub_el_hizb_number": 165,
      "ruku_number": 360,
      "manzil_number": 5,
      "sajdah_number": null,
      "text_uthmani": "تَنزِيلُ ٱلْكِتَـٰبِ لَا رَيْبَ فِيهِ مِن رَّبِّ ٱلْعَـٰلَمِينَ",
      "text_uthmani_tajweed": "تَ<tajweed class=ikhafa>نز</tajweed>ِيلُ <tajweed class=ham_wasl>ٱ</tajweed>لْكِتَ<tajweed class=madda_normal>ـٰ</tajweed>بِ لَا رَيْبَ فِيهِ م<tajweed class=idgham_wo_ghunnah>ِن ر</tajweed>َّبِّ <tajweed class=ham_wasl>ٱ</tajweed>لْعَ<tajweed class=madda_normal>ـٰ</tajweed>لَم<tajweed class=madda_permissible>ِي</tajweed>نَ <span class=end>٢</span>",
      "page_number": 415,
      "juz_number": 21,
      "audio": {
        "url": "Alafasy/mp3/032002.mp3",
        "segments": [
          [
            0,
            1,
            50,
            1630
          ],
          [
            1,
            2,
            1640,
            2530
          ],
          [
            2,
            3,
            2540,
            2810
          ],
          [
            3,
            4,
            2820,
            3370
          ],
          [
            4,
            5,
            3380,
            3980
          ],
          [
            5,
            6,
            3990,
            4120
          ],
          [
            6,
            7,
            4130,
            4900
          ],
          [
            7,
            8,
            4910,
            7250
          ]
        ]
      },
      "translations": [
        {
          "id": 661448,
          "resource_id": 101,
          "text": "Бу Китобнинг (яъни, Қуръоннинг) нозил қилиниши, ҳеч шак-шубҳасиз, барча оламларнинг Парвардигори томонидандир."
        }
      ],
      "audio_url": "https://audio.quran.com/reciters/7/Alafasy/mp3/032002.mp3"
    },
    {
      "id": 3506,
      "verse_number": 3,
      "verse_key": "32:3",
      "hizb_number": 42,
      "rub_el_hizb_number": 165,
      "ruku_number": 360,
      "manzil_number": 5,
      "sajdah_number": null,
      "text_uthmani": "أَمْ يَقُولُونَ ٱفْتَرَىٰهُ ۚ بَلْ هُوَ ٱلْحَقُّ مِن رَّبِّكَ لِتُنذِرَ قَوْمًا مَّآ أَتَىٰهُم مِّن نَّذِيرٍ مِّن قَبْلِكَ لَعَلَّهُمْ يَهْتَدُونَ",
      "text_uthmani_tajweed": "أَمْ يَقُولُونَ <tajweed class=ham_wasl>ٱ</tajweed>فْتَرَ>ٮٰ</tajweed>هُ‌ۚ بَلْ هُوَ <tajweed class=ham_wasl>ٱ</tajweed>لْحَقُّ م<tajweed class=idgham_wo_ghunnah>ِن ر</tajweed>َّبِّكَ لِتُ<tajweed class=ikhafa>نذ</tajweed>ِرَ قَوْ<tajweed class=idgham_ghunnah>مًا م</tajweed>ّ<tajweed class=madda_obligatory>َآ</tajweed> أَتَ<tajweed class=madda_normal>ـٰ</tajweed>ه<tajweed class=idgham_shafawi>ُم م</tajweed>ّ<tajweed class=idgham_ghunnah>ِن ن</tajweed>َّذِي<tajweed class=idgham_ghunnah>رٍ م</tajweed>ِّ<tajweed class=ikhafa>ن ق</tajweed>َ<tajweed class=qalaqah>بْ</tajweed>لِكَ لَعَلَّهُمْ يَهْتَد<tajweed class=madda_permissible>ُو</tajweed>نَ <span class=end>٣</span>",
      "page_number": 415,
      "juz_number": 21,
      "audio": {
        "url": "Alafasy/mp3/032003.mp3",
        "segments": [
          [
            0,
            1,
            30,
            310
          ],
          [
            1,
            2,
            320,
            1330
          ],
          [
            2,
            3,
            1340,
            3570
          ],
          [
            3,
            4,
            3580,
            3890
          ],
          [
            4,
            5,
            3900,
            4230
          ],
          [
            5,
            6,
            4240,
            4960
          ],
          [
            6,
            7,
            4970,
            5080
          ],
          [
            7,
            8,
            5090,
            6000
          ],
          [
            8,
            9,
            6010,
            7390
          ],
          [
            9,
            10,
            7400,
            7860
          ],
          [
            10,
            11,
            7870,
            9140
          ],
          [
            11,
            12,
            9150,
            12470
          ],
          [
            12,
            13,
            12480,
            13050
          ],
          [
            13,
            14,
            13060,
            14390
          ],
          [
            14,
            15,
            14400,
            15030
          ],
          [
            15,
            16,
            15040,
            15800
          ],
          [
            16,
            17,
            15810,
            16900
          ],
          [
            17,
            18,
            16910,
            19010
          ]
        ]
      },
      "translations": [
        {
          "id": 661449,
          "resource_id": 101,
          "text": "Балки «Уни (Муҳаммаднинг ўзи) тўқиб олган», дерлар. Йўқ, у (яъни, Қуръон) сиздан илгари бирон огоҳлантиргувчи келмаган қавмни (Охират азобидан) огоҳлантиришингиз учун Парвардигорингиз томонидан (нозил қилинган) Ҳақиқатдир. Шояд улар ҳидоят топсалар."
        }
      ],
      "audio_url": "https://audio.quran.com/reciters/7/Alafasy/mp3/032003.mp3"
    },
    {
      "id": 3507,
      "verse_number": 4,
      "verse_key": "32:4",
      "hizb_number": 42,
      "rub_el_hizb_number": 165,
      "ruku_number": 360,
      "manzil_number": 5,
      "sajdah_number": null,
      "text_uthmani": "ٱللَّهُ ٱلَّذِى خَلَقَ ٱلسَّمَـٰوَٰتِ وَٱلْأَرْضَ وَمَا بَيْنَهُمَا فِى سِتَّةِ أَيَّامٍ ثُمَّ ٱسْتَوَىٰ عَلَى ٱلْعَرْشِ ۖ مَا لَكُم مِّن دُونِهِۦ مِن وَلِىٍّ وَلَا شَفِيعٍ ۚ أَفَلَا تَتَذَكَّرُونَ",
      "text_uthmani_tajweed": "ٱللَّهُ <tajweed class=ham_wasl>ٱ</tajweed>لَّذِى خَلَقَ <tajweed class=ham_wasl>ٱ</tajweed><tajweed class=laam_shamsiyah>ل</tajweed>سَّمَ<tajweed class=madda_normal>ـٰ</tajweed>و<tajweed class=madda_normal>َٲ</tajweed>تِ وَ<tajweed class=ham_wasl>ٱ</tajweed>لْأَرْضَ وَمَا بَيْنَهُمَا فِى سِتَّةِ أَيَّا<tajweed class=ikhafa>مٍ ث</tajweed>ُ<tajweed class=ghunnah>مّ</tajweed>َ <tajweed class=ham_wasl>ٱ</tajweed>سْتَوَىٰ عَلَى <tajweed class=ham_wasl>ٱ</tajweed>لْعَرْشِ‌ۖ مَا لَك<tajweed class=idgham_shafawi>ُم م</tajweed>ِّ<tajweed class=ikhafa>ن د</tajweed>ُونِه<tajweed class=madda_normal>ِۦ</tajweed> م<tajweed class=idgham_ghunnah>ِن و</tajweed>َلِ<tajweed class=idgham_ghunnah>ىٍّ و</tajweed>َلَا شَفِيعٍ‌ۚ أَفَلَا تَتَذَكَّر<tajweed class=madda_permissible>ُو</tajweed>نَ <span class=end>٤</span>",
      "page_number": 415,
      "juz_number": 21,
      "audio": {
        "url": "Alafasy/mp3/032004.mp3",
        "segments": [
          [
            0,
            1,
            200,
            1020
          ],
          [
            1,
            2,
            1030,
            1690
          ],
          [
            2,
            3,
            1700,
            2250
          ],
          [
            3,
            4,
            2260,
            3570
          ],
          [
            4,
            5,
            3580,
            4430
          ],
          [
            5,
            6,
            4440,
            4950
          ],
          [
            6,
            7,
            4960,
            6030
          ],
          [
            7,
            8,
            6040,
            6410
          ],
          [
            8,
            9,
            6420,
            7170
          ],
          [
            9,
            10,
            7180,
            8700
          ],
          [
            10,
            11,
            8710,
            9810
          ],
          [
            11,
            12,
            9820,
            10540
          ],
          [
            12,
            13,
            10550,
            10960
          ],
          [
            13,
            14,
            10970,
            12320
          ],
          [
            14,
            15,
            12330,
            12720
          ],
          [
            15,
            16,
            12730,
            13970
          ],
          [
            16,
            17,
            13980,
            15010
          ],
          [
            17,
            18,
            15020,
            15960
          ],
          [
            18,
            19,
            15970,
            16930
          ],
          [
            19,
            20,
            16940,
            17740
          ],
          [
            20,
            21,
            17750,
            18870
          ],
          [
            21,
            22,
            18880,
            21250
          ],
          [
            22,
            23,
            21260,
            21920
          ],
          [
            23,
            24,
            21930,
            24580
          ]
        ]
      },
      "translations": [
        {
          "id": 661450,
          "resource_id": 101,
          "text": "Аллоҳ осмонлар ва Ерни ҳамда уларнинг ўртасидаги бор нарсани олти кунда яратиб, сўнгра (Зоти ва Улуғлигига муносиб суратда) Аршга юксалган Зотдир. Сизлар учун Ундан ўзга бирон дўст ва оқловчи йўқдир. Ахир эслатма-ибрат олмайсизларми?!"
        }
      ],
      "audio_url": "https://audio.quran.com/reciters/7/Alafasy/mp3/032004.mp3"
    },
    {
      "id": 3508,
      "verse_number": 5,
      "verse_key": "32:5",
      "hizb_number": 42,
      "rub_el_hizb_number": 165,
      "ruku_number": 360,
      "manzil_number": 5,
      "sajdah_number": null,
      "text_uthmani": "يُدَبِّرُ ٱلْأَمْرَ مِنَ ٱلسَّمَآءِ إِلَى ٱلْأَرْضِ ثُمَّ يَعْرُجُ إِلَيْهِ فِى يَوْمٍ كَانَ مِقْدَارُهُۥٓ أَلْفَ سَنَةٍ مِّمَّا تَعُدُّونَ",
      "text_uthmani_tajweed": "يُدَبِّرُ <tajweed class=ham_wasl>ٱ</tajweed>لْأَمْرَ مِنَ <tajweed class=ham_wasl>ٱ</tajweed><tajweed class=laam_shamsiyah>ل</tajweed>سَّم<tajweed class=madda_obligatory>َا</tajweed>ٓءِ إِلَى <tajweed class=ham_wasl>ٱ</tajweed>لْأَرْضِ ثُ<tajweed class=ghunnah>مّ</tajweed>َ يَعْرُجُ إِلَيْهِ فِى يَوْ<tajweed class=ikhafa>مٍ ك</tajweed>َانَ مِ<tajweed class=qalaqah>قْ</tajweed>دَارُهُ<tajweed class=madda_obligatory>ۥٓ</tajweed> أَلْفَ سَنَ<tajweed class=idgham_ghunnah>ةٍ م</tajweed>ِّ<tajweed class=ghunnah>مّ</tajweed>َا تَعُدّ<tajweed class=madda_permissible>ُو</tajweed>نَ <span class=end>٥</span>",
      "page_number": 415,
      "juz_number": 21,
      "audio": {
        "url": "Alafasy/mp3/032005.mp3",
        "segments": [
          [
            0,
            1,
            60,
            930
          ],
          [
            1,
            2,
            940,
            1640
          ],
          [
            2,
            3,
            1650,
            1940
          ],
          [
            3,
            4,
            1950,
            4180
          ],
          [
            4,
            5,
            4190,
            4490
          ],
          [
            5,
            6,
            4500,
            5180
          ],
          [
            6,
            7,
            5190,
            6480
          ],
          [
            7,
            8,
            6490,
            7230
          ],
          [
            8,
            9,
            7240,
            7850
          ],
          [
            9,
            10,
            7860,
            8270
          ],
          [
            10,
            11,
            8280,
            9560
          ],
          [
            11,
            12,
            9570,
            10160
          ],
          [
            12,
            13,
            10170,
            14700
          ],
          [
            13,
            14,
            14710,
            15130
          ],
          [
            14,
            15,
            15140,
            16560
          ],
          [
            15,
            16,
            16570,
            17840
          ],
          [
            16,
            17,
            17850,
            19990
          ]
        ]
      },
      "translations": [
        {
          "id": 661451,
          "resource_id": 101,
          "text": "У осмондан ергача бўлган барча ишни тадбир қилиб — бошқариб турур, сўнгра (бу ишларнинг барчаси) сизларнинг ҳисобингизга минг йилга тенг бўладиган бир кунда (яъни, Қиёматда) Унинг Ўзига кўтарилур. <sup foot_note=145181>1</sup>"
        }
      ],
      "audio_url": "https://audio.quran.com/reciters/7/Alafasy/mp3/032005.mp3"
    },
    {
      "id": 3509,
      "verse_number": 6,
      "verse_key": "32:6",
      "hizb_number": 42,
      "rub_el_hizb_number": 165,
      "ruku_number": 360,
      "manzil_number": 5,
      "sajdah_number": null,
      "text_uthmani": "ذَٰلِكَ عَـٰلِمُ ٱلْغَيْبِ وَٱلشَّهَـٰدَةِ ٱلْعَزِيزُ ٱلرَّحِيمُ",
      "text_uthmani_tajweed": "ذ<tajweed class=madda_normal>َٲ</tajweed>لِكَ عَ<tajweed class=madda_normal>ـٰ</tajweed>لِمُ <tajweed class=ham_wasl>ٱ</tajweed>لْغَيْبِ وَ<tajweed class=ham_wasl>ٱ</tajweed><tajweed class=laam_shamsiyah>ل</tajweed>شَّهَ<tajweed class=madda_normal>ـٰ</tajweed>دَةِ <tajweed class=ham_wasl>ٱ</tajweed>لْعَزِيزُ <tajweed class=ham_wasl>ٱ</tajweed><tajweed class=laam_shamsiyah>ل</tajweed>رَّح<tajweed class=madda_permissible>ِي</tajweed>مُ <span class=end>٦</span>",
      "page_number": 415,
      "juz_number": 21,
      "audio": {
        "url": "Alafasy/mp3/032006.mp3",
        "segments": [
          [
            0,
            1,
            70,
            740
          ],
          [
            1,
            2,
            750,
            1530
          ],
          [
            2,
            3,
            1540,
            2260
          ],
          [
            3,
            4,
            2270,
            3530
          ],
          [
            4,
            5,
            3540,
            4440
          ],
          [
            5,
            6,
            4450,
            6500
          ]
        ]
      },
      "translations": [
        {
          "id": 661452,
          "resource_id": 101,
          "text": "Мана шу (Аллоҳ) ғойиб ва ҳозирни билгувчи, қудратли ва меҳрибондир."
        }
      ],
      "audio_url": "https://audio.quran.com/reciters/7/Alafasy/mp3/032006.mp3"
    },
    {
      "id": 3510,
      "verse_number": 7,
      "verse_key": "32:7",
      "hizb_number": 42,
      "rub_el_hizb_number": 165,
      "ruku_number": 360,
      "manzil_number": 5,
      "sajdah_number": null,
      "text_uthmani": "ٱلَّذِىٓ أَحْسَنَ كُلَّ شَىْءٍ خَلَقَهُۥ ۖ وَبَدَأَ خَلْقَ ٱلْإِنسَـٰنِ مِن طِينٍ",
      "text_uthmani_tajweed": "ٱلَّذ<tajweed class=madda_obligatory>ِىٓ</tajweed> أَحْسَنَ كُلَّ شَىْءٍ خَلَقَهُ<tajweed class=madda_normal>ۥ</tajweed>‌ۖ وَبَدَأَ خَلْقَ <tajweed class=ham_wasl>ٱ</tajweed>لْإِ<tajweed class=ikhafa>نس</tajweed>َ<tajweed class=madda_normal>ـٰ</tajweed>نِ مِ<tajweed class=ikhafa>ن ط</tajweed><tajweed class=madda_permissible>ِي</tajweed>نٍ <span class=end>٧</span>",
      "page_number": 415,
      "juz_number": 21,
      "audio": {
        "url": "Alafasy/mp3/032007.mp3",
        "segments": [
          [
            0,
            1,
            150,
            2130
          ],
          [
            1,
            2,
            2140,
            2840
          ],
          [
            2,
            3,
            2850,
            3340
          ],
          [
            3,
            4,
            3350,
            4080
          ],
          [
            4,
            5,
            4090,
            5250
          ],
          [
            5,
            6,
            5260,
            5870
          ],
          [
            6,
            7,
            5880,
            6480
          ],
          [
            7,
            8,
            6490,
            8220
          ],
          [
            8,
            9,
            8230,
            9330
          ],
          [
            9,
            10,
            9340,
            10890
          ]
        ]
      },
      "translations": [
        {
          "id": 661453,
          "resource_id": 101,
          "text": "У барча нарсани чиройли қилиб яратган Зотдир. У инсонни (яъни, Одамни) даставвал лойдан яратди. <sup foot_note=145182>1</sup>"
        }
      ],
      "audio_url": "https://audio.quran.com/reciters/7/Alafasy/mp3/032007.mp3"
    },
    {
      "id": 3511,
      "verse_number": 8,
      "verse_key": "32:8",
      "hizb_number": 42,
      "rub_el_hizb_number": 165,
      "ruku_number": 360,
      "manzil_number": 5,
      "sajdah_number": null,
      "text_uthmani": "ثُمَّ جَعَلَ نَسْلَهُۥ مِن سُلَـٰلَةٍ مِّن مَّآءٍ مَّهِينٍ",
      "text_uthmani_tajweed": "ثُ<tajweed class=ghunnah>مّ</tajweed>َ جَعَلَ نَسْلَهُ<tajweed class=madda_normal>ۥ</tajweed> مِ<tajweed class=ikhafa>ن س</tajweed>ُلَ<tajweed class=madda_normal>ـٰ</tajweed>لَ<tajweed class=idgham_ghunnah>ةٍ م</tajweed>ّ<tajweed class=idgham_ghunnah>ِن م</tajweed>ّ<tajweed class=madda_obligatory>َا</tajweed>ٓ<tajweed class=idgham_ghunnah>ءٍ م</tajweed>َّه<tajweed class=madda_permissible>ِي</tajweed>نٍ <span class=end>٨</span>",
      "page_number": 415,
      "juz_number": 21,
      "audio": {
        "url": "Alafasy/mp3/032008.mp3",
        "segments": [
          [
            0,
            1,
            30,
            1140
          ],
          [
            1,
            2,
            1150,
            1740
          ],
          [
            2,
            3,
            1750,
            2590
          ],
          [
            3,
            4,
            2600,
            3390
          ],
          [
            4,
            5,
            3400,
            5130
          ],
          [
            5,
            6,
            5140,
            7030
          ],
          [
            6,
            7,
            7040,
            8530
          ],
          [
            7,
            8,
            8540,
            10100
          ]
        ]
      },
      "translations": [
        {
          "id": 661454,
          "resource_id": 101,
          "text": "Сўнгра унинг насли авлодини ҳақир бир сувдан (иборат бўлган нутфадан пайдо) қилди."
        }
      ],
      "audio_url": "https://audio.quran.com/reciters/7/Alafasy/mp3/032008.mp3"
    },
    {
      "id": 3512,
      "verse_number": 9,
      "verse_key": "32:9",
      "hizb_number": 42,
      "rub_el_hizb_number": 165,
      "ruku_number": 360,
      "manzil_number": 5,
      "sajdah_number": null,
      "text_uthmani": "ثُمَّ سَوَّىٰهُ وَنَفَخَ فِيهِ مِن رُّوحِهِۦ ۖ وَجَعَلَ لَكُمُ ٱلسَّمْعَ وَٱلْأَبْصَـٰرَ وَٱلْأَفْـِٔدَةَ ۚ قَلِيلًا مَّا تَشْكُرُونَ",
      "text_uthmani_tajweed": "ثُ<tajweed class=ghunnah>مّ</tajweed>َ سَوَّ<tajweed class=madda_normal>ٮٰ</tajweed>هُ وَنَفَخَ فِيهِ م<tajweed class=idgham_wo_ghunnah>ِن ر</tajweed>ُّوحِه<tajweed class=madda_normal>ِۦ</tajweed>‌ۖ وَجَعَلَ لَكُمُ <tajweed class=ham_wasl>ٱ</tajweed><tajweed class=laam_shamsiyah>ل</tajweed>سَّمْعَ وَ<tajweed class=ham_wasl>ٱ</tajweed>لْأَ<tajweed class=qalaqah>بْ</tajweed>صَ<tajweed class=madda_normal>ـٰ</tajweed>رَ وَ<tajweed class=ham_wasl>ٱ</tajweed>لْأَفْــِٔدَةَ‌ۚ قَلِيل<tajweed class=idgham_ghunnah>اً م</tajweed>َّا تَشْكُر<tajweed class=madda_permissible>ُو</tajweed>نَ <span class=end>٩</span>",
      "page_number": 415,
      "juz_number": 21,
      "audio": {
        "url": "Alafasy/mp3/032009.mp3",
        "segments": [
          [
            0,
            1,
            50,
            1190
          ],
          [
            1,
            2,
            1200,
            2140
          ],
          [
            2,
            3,
            2150,
            2860
          ],
          [
            3,
            4,
            2870,
            3460
          ],
          [
            4,
            5,
            3470,
            3560
          ],
          [
            5,
            6,
            3570,
            4860
          ],
          [
            6,
            7,
            4870,
            5460
          ],
          [
            7,
            8,
            5470,
            6090
          ],
          [
            8,
            9,
            6100,
            6880
          ],
          [
            9,
            10,
            6890,
            8190
          ],
          [
            10,
            11,
            8200,
            9640
          ],
          [
            11,
            12,
            9650,
            10370
          ],
          [
            12,
            13,
            10380,
            11510
          ],
          [
            13,
            14,
            11520,
            13940
          ]
        ]
      },
      "translations": [
        {
          "id": 661455,
          "resource_id": 101,
          "text": "Сўнгра уни (инсон қилиб) ростлаб, ичига Ўз (даргоҳидаги) жондан киритди. У зот сизлар учун қулоқ, кўз, дилларни пайдо қилди. Сизлар эса камдан-кам шукр қилурсизлар."
        }
      ],
      "audio_url": "https://audio.quran.com/reciters/7/Alafasy/mp3/032009.mp3"
    },
    {
      "id": 3513,
      "verse_number": 10,
      "verse_key": "32:10",
      "hizb_number": 42,
      "rub_el_hizb_number": 165,
      "ruku_number": 360,
      "manzil_number": 5,
      "sajdah_number": null,
      "text_uthmani": "وَقَالُوٓا۟ أَءِذَا ضَلَلْنَا فِى ٱلْأَرْضِ أَءِنَّا لَفِى خَلْقٍ جَدِيدٍۭ ۚ بَلْ هُم بِلِقَآءِ رَبِّهِمْ كَـٰفِرُونَ",
      "text_uthmani_tajweed": "وَقَال<tajweed class=madda_obligatory>ُوٓ</tajweed><tajweed class=slnt>اْ</tajweed> أَءِذَا ضَلَلْنَا فِى <tajweed class=ham_wasl>ٱ</tajweed>لْأَرْضِ أَءِ<tajweed class=ghunnah>نّ</tajweed>َا لَفِى خَلْ<tajweed class=ikhafa>قٍ ج</tajweed>َدِي<tajweed class=iqlab>دِۭ‌ۚ ب</tajweed>َلْ ه<tajweed class=ikhafa_shafawi>ُم ب</tajweed>ِلِق<tajweed class=madda_obligatory>َا</tajweed>ٓءِ رَبِّهِمْ كَ<tajweed class=madda_normal>ـٰ</tajweed>فِر<tajweed class=madda_permissible>ُو</tajweed>نَ <span class=end>١٠</span>",
      "page_number": 415,
      "juz_number": 21,
      "audio": {
        "url": "Alafasy/mp3/032010.mp3",
        "segments": [
          [
            0,
            1,
            30,
            1730
          ],
          [
            1,
            2,
            1740,
            2360
          ],
          [
            2,
            3,
            2370,
            3310
          ],
          [
            3,
            4,
            3320,
            3550
          ],
          [
            4,
            5,
            3560,
            4320
          ],
          [
            5,
            6,
            4330,
            5910
          ],
          [
            6,
            7,
            5920,
            6400
          ],
          [
            7,
            8,
            6410,
            7950
          ],
          [
            8,
            9,
            7960,
            10570
          ],
          [
            9,
            10,
            10580,
            10890
          ],
          [
            10,
            11,
            10900,
            12120
          ],
          [
            11,
            12,
            12130,
            14510
          ],
          [
            12,
            13,
            14520,
            15450
          ],
          [
            13,
            14,
            15460,
            18080
          ]
        ]
      },
      "translations": [
        {
          "id": 661456,
          "resource_id": 101,
          "text": "Улар (яъни, кофирлар): «Бизлар ер (остида) йўқ бўлиб кетгач, ҳақиқатан ҳам яна янги яралиш билан яралурмизми?», дедилар. Йўқ, улар Парвардигорга рўбарў бўлишни инкор қилгувчидирлар."
        }
      ],
      "audio_url": "https://audio.quran.com/reciters/7/Alafasy/mp3/032010.mp3"
    },
    {
      "id": 3514,
      "verse_number": 11,
      "verse_key": "32:11",
      "hizb_number": 42,
      "rub_el_hizb_number": 166,
      "ruku_number": 360,
      "manzil_number": 5,
      "sajdah_number": null,
      "text_uthmani": "۞ قُلْ يَتَوَفَّىٰكُم مَّلَكُ ٱلْمَوْتِ ٱلَّذِى وُكِّلَ بِكُمْ ثُمَّ إِلَىٰ رَبِّكُمْ تُرْجَعُونَ",
      "text_uthmani_tajweed": "۞ قُلْ يَتَوَفَّ<tajweed class=madda_normal>ـٰ</tajweed>ك<tajweed class=idgham_shafawi>ُم م</tajweed>َّلَكُ <tajweed class=ham_wasl>ٱ</tajweed>لْمَوْتِ <tajweed class=ham_wasl>ٱ</tajweed>لَّذِى وُكِّلَ بِكُمْ ثُ<tajweed class=ghunnah>مّ</tajweed>َ إِلَىٰ رَبِّكُمْ تُرْجَع<tajweed class=madda_permissible>ُو</tajweed>نَ <span class=end>١١</span>",
      "page_number": 415,
      "juz_number": 21,
      "audio": {
        "url": "Alafasy/mp3/032011.mp3",
        "segments": [
          [
            0,
            1,
            40,
            290
          ],
          [
            1,
            2,
            300,
            2780
          ],
          [
            2,
            3,
            2790,
            3270
          ],
          [
            3,
            4,
            3280,
            4020
          ],
          [
            4,
            5,
            4030,
            4750
          ],
          [
            5,
            6,
            4760,
            5460
          ],
          [
            6,
            7,
            5470,
            6010
          ],
          [
            7,
            8,
            6020,
            7400
          ],
          [
            8,
            9,
            7410,
            7910
          ],
          [
            9,
            10,
            7920,
            8880
          ],
          [
            10,
            11,
            8890,
            11470
          ]
        ]
      },
      "translations": [
        {
          "id": 661457,
          "resource_id": 101,
          "text": "(Эй Муҳаммад алайҳис-салоту вас-салом), айтинг: «Сизларга вакил қилинган ўлим фариштаси жонларингизни олур, сўнгра Парвардигорингизга қайтарилурсизлар»."
        }
      ],
      "audio_url": "https://audio.quran.com/reciters/7/Alafasy/mp3/032011.mp3"
    },
    {
      "id": 3515,
      "verse_number": 12,
      "verse_key": "32:12",
      "hizb_number": 42,
      "rub_el_hizb_number": 166,
      "ruku_number": 361,
      "manzil_number": 5,
      "sajdah_number": null,
      "text_uthmani": "وَلَوْ تَرَىٰٓ إِذِ ٱلْمُجْرِمُونَ نَاكِسُوا۟ رُءُوسِهِمْ عِندَ رَبِّهِمْ رَبَّنَآ أَبْصَرْنَا وَسَمِعْنَا فَٱرْجِعْنَا نَعْمَلْ صَـٰلِحًا إِنَّا مُوقِنُونَ",
      "text_uthmani_tajweed": "وَلَوْ تَرَ<tajweed class=madda_obligatory>ىٰٓ</tajweed> إِذِ <tajweed class=ham_wasl>ٱ</tajweed>لْمُ<tajweed class=qalaqah>جْ</tajweed>رِمُونَ نَاكِسُو<tajweed class=slnt>اْ</tajweed> رُءُوسِهِمْ عِ<tajweed class=ikhafa>ند</tajweed>َ رَبِّهِمْ رَبَّن<tajweed class=madda_obligatory>َآ</tajweed> أَ<tajweed class=qalaqah>بْ</tajweed>صَرْنَا وَسَمِعْنَا فَ<tajweed class=ham_wasl>ٱ</tajweed>رْجِعْنَا نَعْمَلْ صَ<tajweed class=madda_normal>ـٰ</tajweed>لِحًا إِ<tajweed class=ghunnah>نّ</tajweed>َا مُوقِن<tajweed class=madda_permissible>ُو</tajweed>نَ <span class=end>١٢</span>",
      "page_number": 416,
      "juz_number": 21,
      "audio": {
        "url": "Alafasy/mp3/032012.mp3",
        "segments": [
          [
            0,
            1,
            30,
            510
          ],
          [
            1,
            2,
            520,
            2610
          ],
          [
            2,
            3,
            2620,
            3000
          ],
          [
            3,
            4,
            3010,
            4280
          ],
          [
            4,
            5,
            4290,
            5200
          ],
          [
            5,
            6,
            5210,
            6250
          ],
          [
            6,
            7,
            6260,
            7590
          ],
          [
            7,
            8,
            7600,
            8500
          ],
          [
            8,
            9,
            8510,
            10480
          ],
          [
            9,
            10,
            10490,
            11810
          ],
          [
            10,
            11,
            11820,
            12890
          ],
          [
            11,
            12,
            12900,
            15690
          ],
          [
            12,
            13,
            15700,
            16310
          ],
          [
            13,
            14,
            16320,
            17300
          ],
          [
            14,
            15,
            17310,
            18640
          ],
          [
            15,
            16,
            18650,
            21320
          ]
        ]
      },
      "translations": [
        {
          "id": 661458,
          "resource_id": 101,
          "text": "Агар сиз у жиноятчи кимсаларни (Қиёмат Кунида) Парвардигорлари ҳузурида бошлари эгик ҳолда туриб: «Парвардигоро, (ваъданг рост эканлигини) кўрдик ва эшитдик, бас, бизларни (ҳаётга) қайтаргин, бизлар яхши амал қилайлик. Энди бизлар (Қиёмат ҳақ эканлигига) шак-шубҳасиз, ишонгувчидирмиз», (дейишларини) кўрсангиз эди."
        }
      ],
      "audio_url": "https://audio.quran.com/reciters/7/Alafasy/mp3/032012.mp3"
    },
    {
      "id": 3516,
      "verse_number": 13,
      "verse_key": "32:13",
      "hizb_number": 42,
      "rub_el_hizb_number": 166,
      "ruku_number": 361,
      "manzil_number": 5,
      "sajdah_number": null,
      "text_uthmani": "وَلَوْ شِئْنَا لَـَٔاتَيْنَا كُلَّ نَفْسٍ هُدَىٰهَا وَلَـٰكِنْ حَقَّ ٱلْقَوْلُ مِنِّى لَأَمْلَأَنَّ جَهَنَّمَ مِنَ ٱلْجِنَّةِ وَٱلنَّاسِ أَجْمَعِينَ",
      "text_uthmani_tajweed": "وَلَوْ شِئْنَا لَأَتَيْنَا كُلَّ نَفْسٍ هُدَ<tajweed class=madda_normal>ٮٰ</tajweed>هَا وَلَ<tajweed class=madda_normal>ـٰ</tajweed>كِنْ حَقَّ <tajweed class=ham_wasl>ٱ</tajweed>لْقَوْلُ مِ<tajweed class=ghunnah>نّ</tajweed>ِى لَأَمْلَأَ<tajweed class=ghunnah>نّ</tajweed>َ جَهَ<tajweed class=ghunnah>نّ</tajweed>َمَ مِنَ <tajweed class=ham_wasl>ٱ</tajweed>لْجِ<tajweed class=ghunnah>نّ</tajweed>َةِ وَ<tajweed class=ham_wasl>ٱ</tajweed><tajweed class=laam_shamsiyah>ل</tajweed><tajweed class=ghunnah>نّ</tajweed>َاسِ أَ<tajweed class=qalaqah>جْ</tajweed>مَع<tajweed class=madda_permissible>ِي</tajweed>نَ <span class=end>١٣</span>",
      "page_number": 416,
      "juz_number": 21,
      "audio": {
        "url": "Alafasy/mp3/032013.mp3",
        "segments": [
          [
            0,
            1,
            60,
            530
          ],
          [
            1,
            2,
            540,
            1330
          ],
          [
            2,
            3,
            1340,
            2580
          ],
          [
            3,
            4,
            2590,
            3210
          ],
          [
            4,
            5,
            3220,
            3890
          ],
          [
            5,
            6,
            3900,
            4780
          ],
          [
            6,
            7,
            4790,
            5690
          ],
          [
            7,
            8,
            5700,
            6300
          ],
          [
            8,
            9,
            6310,
            7030
          ],
          [
            9,
            10,
            7040,
            12380
          ],
          [
            10,
            11,
            12390,
            14180
          ],
          [
            11,
            12,
            14190,
            15380
          ],
          [
            12,
            13,
            15390,
            15970
          ],
          [
            13,
            14,
            15980,
            17600
          ],
          [
            14,
            15,
            17610,
            19310
          ],
          [
            15,
            16,
            19320,
            21580
          ]
        ]
      },
      "translations": [
        {
          "id": 661459,
          "resource_id": 101,
          "text": "Агар Биз хоҳласак, албатта ҳар бир жонга ўз ҳидоятини ато этган бўлур эдик, лекин Мен томондан бу сўз ҳақ-собит бўлгандир: «Мен жаҳаннамни (кофир) жин ва (динсиз) одамларнинг барчаси билан тўлдирурман». <sup foot_note=145183>1</sup>"
        }
      ],
      "audio_url": "https://audio.quran.com/reciters/7/Alafasy/mp3/032013.mp3"
    },
    {
      "id": 3517,
      "verse_number": 14,
      "verse_key": "32:14",
      "hizb_number": 42,
      "rub_el_hizb_number": 166,
      "ruku_number": 361,
      "manzil_number": 5,
      "sajdah_number": null,
      "text_uthmani": "فَذُوقُوا۟ بِمَا نَسِيتُمْ لِقَآءَ يَوْمِكُمْ هَـٰذَآ إِنَّا نَسِينَـٰكُمْ ۖ وَذُوقُوا۟ عَذَابَ ٱلْخُلْدِ بِمَا كُنتُمْ تَعْمَلُونَ",
      "text_uthmani_tajweed": "فَذُوقُو<tajweed class=slnt>اْ</tajweed> بِمَا نَسِيتُمْ لِق<tajweed class=madda_obligatory>َا</tajweed>ٓءَ يَوْمِكُمْ هَ<tajweed class=madda_normal>ـٰ</tajweed>ذ<tajweed class=madda_obligatory>َآ</tajweed> إِ<tajweed class=ghunnah>نّ</tajweed>َا نَسِينَ<tajweed class=madda_normal>ـٰ</tajweed>كُمْ‌ۖ وَذُوقُو<tajweed class=slnt>اْ</tajweed> عَذَابَ <tajweed class=ham_wasl>ٱ</tajweed>لْخُلْدِ بِمَا كُ<tajweed class=ikhafa>نت</tajweed>ُمْ تَعْمَل<tajweed class=madda_permissible>ُو</tajweed>نَ <span class=end>١٤</span>",
      "page_number": 416,
      "juz_number": 21,
      "audio": {
        "url": "Alafasy/mp3/032014.mp3",
        "segments": [
          [
            0,
            1,
            30,
            890
          ],
          [
            1,
            2,
            900,
            1450
          ],
          [
            2,
            3,
            1460,
            2370
          ],
          [
            3,
            4,
            2380,
            4610
          ],
          [
            4,
            5,
            4620,
            5510
          ],
          [
            5,
            6,
            5520,
            7600
          ],
          [
            6,
            7,
            7610,
            9080
          ],
          [
            7,
            8,
            9090,
            10770
          ],
          [
            8,
            9,
            10780,
            11600
          ],
          [
            9,
            10,
            11610,
            12440
          ],
          [
            10,
            11,
            12450,
            13220
          ],
          [
            11,
            12,
            13230,
            13680
          ],
          [
            12,
            13,
            13690,
            15000
          ],
          [
            13,
            14,
            15010,
            17490
          ]
        ]
      },
      "translations": [
        {
          "id": 661460,
          "resource_id": 101,
          "text": "Бас, (эй кофирлар), ушбу кунингиздаги учрашувни унутиб қўйганларингиз сабабли (аламли азобни) тотингиз! Дарвоқеъ, Биз ҳам (бугун) сизларни «унутдик». Қилиб ўтган амалларингиз сабабли мангу азобни тотингиз!"
        }
      ],
      "audio_url": "https://audio.quran.com/reciters/7/Alafasy/mp3/032014.mp3"
    },
    {
      "id": 3518,
      "verse_number": 15,
      "verse_key": "32:15",
      "hizb_number": 42,
      "rub_el_hizb_number": 166,
      "ruku_number": 361,
      "manzil_number": 5,
      "sajdah_number": 9,
      "text_uthmani": "إِنَّمَا يُؤْمِنُ بِـَٔايَـٰتِنَا ٱلَّذِينَ إِذَا ذُكِّرُوا۟ بِهَا خَرُّوا۟ سُجَّدًا وَسَبَّحُوا۟ بِحَمْدِ رَبِّهِمْ وَهُمْ لَا يَسْتَكْبِرُونَ ۩",
      "text_uthmani_tajweed": "إِ<tajweed class=ghunnah>نّ</tajweed>َمَا يُؤْمِنُ بِـَٔـايَ<tajweed class=madda_normal>ـٰ</tajweed>تِنَا <tajweed class=ham_wasl>ٱ</tajweed>لَّذِينَ إِذَا ذُكِّرُو<tajweed class=slnt>اْ</tajweed> بِهَا خَرُّو<tajweed class=slnt>اْ</tajweed> سُجَّ<tajweed class=idgham_ghunnah>دًا و</tajweed>َسَبَّحُو<tajweed class=slnt>اْ</tajweed> بِحَمْدِ رَبِّهِمْ وَهُمْ لَا يَسْتَكْبِرُ<tajweed class=madda_permissible>و</tajweed>نَ ۩ <span class=end>١٥</span>",
      "page_number": 416,
      "juz_number": 21,
      "audio": {
        "url": "Alafasy/mp3/032015.mp3",
        "segments": [
          [
            0,
            1,
            30,
            1530
          ],
          [
            1,
            2,
            1540,
            2290
          ],
          [
            2,
            3,
            2300,
            3550
          ],
          [
            3,
            4,
            3560,
            4480
          ],
          [
            4,
            5,
            4490,
            5010
          ],
          [
            5,
            6,
            5020,
            5900
          ],
          [
            6,
            7,
            5910,
            6430
          ],
          [
            7,
            8,
            6440,
            7190
          ],
          [
            8,
            9,
            7200,
            7960
          ],
          [
            9,
            10,
            7970,
            9660
          ],
          [
            10,
            11,
            9670,
            10380
          ],
          [
            11,
            12,
            10390,
            16610
          ],
          [
            12,
            13,
            16620,
            17220
          ],
          [
            13,
            14,
            17230,
            17620
          ],
          [
            14,
            15,
            17630,
            21080
          ]
        ]
      },
      "translations": [
        {
          "id": 661461,
          "resource_id": 101,
          "text": "Бизнинг оятларимизга фақат қачон у (оятлар) зикр қилинса, сажда қилган ҳолларида йиқиладиган ва кибр-ҳаво қилмаган ҳолларида ҳамду сано айтиш билан Парвардигорларини поклайдиган зотларгина иймон келтирурлар. <sup foot_note=145184>1</sup>"
        }
      ],
      "audio_url": "https://audio.quran.com/reciters/7/Alafasy/mp3/032015.mp3"
    },
    {
      "id": 3519,
      "verse_number": 16,
      "verse_key": "32:16",
      "hizb_number": 42,
      "rub_el_hizb_number": 166,
      "ruku_number": 361,
      "manzil_number": 5,
      "sajdah_number": null,
      "text_uthmani": "تَتَجَافَىٰ جُنُوبُهُمْ عَنِ ٱلْمَضَاجِعِ يَدْعُونَ رَبَّهُمْ خَوْفًا وَطَمَعًا وَمِمَّا رَزَقْنَـٰهُمْ يُنفِقُونَ",
      "text_uthmani_tajweed": "تَتَجَافَىٰ جُنُوبُهُمْ عَنِ <tajweed class=ham_wasl>ٱ</tajweed>لْمَضَاجِعِ يَ<tajweed class=qalaqah>دْ</tajweed>عُونَ رَبَّهُمْ خَوْ<tajweed class=idgham_ghunnah>فًا و</tajweed>َطَمَ<tajweed class=idgham_ghunnah>عًا و</tajweed>َمِ<tajweed class=ghunnah>مّ</tajweed>َا رَزَ<tajweed class=qalaqah>قْ</tajweed>نَ<tajweed class=madda_normal>ـٰ</tajweed>هُمْ يُ<tajweed class=ikhafa>نف</tajweed>ِق<tajweed class=madda_permissible>ُو</tajweed>نَ <span class=end>١٦</span>",
      "page_number": 416,
      "juz_number": 21,
      "audio": {
        "url": "Alafasy/mp3/032016.mp3",
        "segments": [
          [
            0,
            1,
            50,
            1250
          ],
          [
            1,
            2,
            1260,
            2450
          ],
          [
            2,
            3,
            2460,
            2860
          ],
          [
            3,
            4,
            2870,
            4180
          ],
          [
            4,
            5,
            4190,
            5190
          ],
          [
            5,
            6,
            5200,
            6140
          ],
          [
            6,
            7,
            6150,
            6820
          ],
          [
            7,
            8,
            6830,
            8290
          ],
          [
            8,
            9,
            8300,
            10570
          ],
          [
            9,
            10,
            10580,
            11990
          ],
          [
            10,
            11,
            12000,
            15210
          ]
        ]
      },
      "translations": [
        {
          "id": 661462,
          "resource_id": 101,
          "text": "Уларнинг ёнбошлари ўрин-жойларидан йироқ бўлур (яъни, тунларини ибодат билан ўтказишиб, оз ухлайдилар). Улар Парвардигорларига қўрқув ва умидворлик билан дуо-илтижо қилурлар ва Биз уларга ризқ қилиб берган нарсалардан инфоқ-эҳсон қилурлар."
        }
      ],
      "audio_url": "https://audio.quran.com/reciters/7/Alafasy/mp3/032016.mp3"
    },
    {
      "id": 3520,
      "verse_number": 17,
      "verse_key": "32:17",
      "hizb_number": 42,
      "rub_el_hizb_number": 166,
      "ruku_number": 361,
      "manzil_number": 5,
      "sajdah_number": null,
      "text_uthmani": "فَلَا تَعْلَمُ نَفْسٌ مَّآ أُخْفِىَ لَهُم مِّن قُرَّةِ أَعْيُنٍ جَزَآءًۢ بِمَا كَانُوا۟ يَعْمَلُونَ",
      "text_uthmani_tajweed": "فَلَا تَعْلَمُ نَفْ<tajweed class=idgham_ghunnah>سٌ م</tajweed>ّ<tajweed class=madda_obligatory>َآ</tajweed> أُخْفِىَ لَه<tajweed class=idgham_shafawi>ُم م</tajweed>ِّ<tajweed class=ikhafa>ن ق</tajweed>ُرَّةِ أَعْيُ<tajweed class=ikhafa>نٍ ج</tajweed>َز<tajweed class=madda_obligatory>َا</tajweed>ٓ<tajweed class=iqlab>ءَۢ ب</tajweed>ِمَا كَانُو<tajweed class=slnt>اْ</tajweed> يَعْمَل<tajweed class=madda_permissible>ُو</tajweed>نَ <span class=end>١٧</span>",
      "page_number": 416,
      "juz_number": 21,
      "audio": {
        "url": "Alafasy/mp3/032017.mp3",
        "segments": [
          [
            0,
            1,
            30,
            590
          ],
          [
            1,
            2,
            600,
            1460
          ],
          [
            2,
            3,
            1470,
            3220
          ],
          [
            3,
            4,
            3230,
            3610
          ],
          [
            4,
            5,
            3620,
            5600
          ],
          [
            5,
            6,
            5610,
            6930
          ],
          [
            6,
            7,
            6940,
            7600
          ],
          [
            7,
            8,
            7610,
            8470
          ],
          [
            8,
            9,
            8480,
            10060
          ],
          [
            9,
            10,
            10070,
            12960
          ],
          [
            10,
            11,
            12970,
            13550
          ],
          [
            11,
            12,
            13560,
            14420
          ],
          [
            12,
            13,
            14430,
            16240
          ]
        ]
      },
      "translations": [
        {
          "id": 661463,
          "resource_id": 101,
          "text": "Бас, уларнинг қилиб ўтган амалларига мукофот қилиб улар учун беркитиб қўйилган кўзлар қувончини (яъни, Охират неъматларини) бирон жон билмас."
        }
      ],
      "audio_url": "https://audio.quran.com/reciters/7/Alafasy/mp3/032017.mp3"
    },
    {
      "id": 3521,
      "verse_number": 18,
      "verse_key": "32:18",
      "hizb_number": 42,
      "rub_el_hizb_number": 166,
      "ruku_number": 361,
      "manzil_number": 5,
      "sajdah_number": null,
      "text_uthmani": "أَفَمَن كَانَ مُؤْمِنًا كَمَن كَانَ فَاسِقًا ۚ لَّا يَسْتَوُۥنَ",
      "text_uthmani_tajweed": "أَفَمَ<tajweed class=ikhafa>ن ك</tajweed>َانَ مُؤْمِ<tajweed class=ikhafa>نًا ك</tajweed>َمَ<tajweed class=ikhafa>ن ك</tajweed>َانَ فَاسِ<tajweed class=idgham_wo_ghunnah>قًا‌ۚ ل</tajweed>َّا يَسْتَوُ<tajweed class=madda_permissible>ۥ</tajweed>نَ <span class=end>١٨</span>",
      "page_number": 416,
      "juz_number": 21,
      "audio": {
        "url": "Alafasy/mp3/032018.mp3",
        "segments": [
          [
            0,
            1,
            30,
            1460
          ],
          [
            1,
            2,
            1470,
            2110
          ],
          [
            2,
            3,
            2120,
            3600
          ],
          [
            3,
            4,
            3610,
            4810
          ],
          [
            4,
            5,
            4820,
            5410
          ],
          [
            5,
            6,
            5420,
            7080
          ],
          [
            6,
            7,
            7090,
            7390
          ],
          [
            7,
            8,
            7400,
            9840
          ]
        ]
      },
      "translations": [
        {
          "id": 661464,
          "resource_id": 101,
          "text": "Ахир мўмин бўлган киши билан фосиқ-итоатсиз бўлган кимса тенг бўлурми? (Йўқ), баробар бўлмаслар!"
        }
      ],
      "audio_url": "https://audio.quran.com/reciters/7/Alafasy/mp3/032018.mp3"
    },
    {
      "id": 3522,
      "verse_number": 19,
      "verse_key": "32:19",
      "hizb_number": 42,
      "rub_el_hizb_number": 166,
      "ruku_number": 361,
      "manzil_number": 5,
      "sajdah_number": null,
      "text_uthmani": "أَمَّا ٱلَّذِينَ ءَامَنُوا۟ وَعَمِلُوا۟ ٱلصَّـٰلِحَـٰتِ فَلَهُمْ جَنَّـٰتُ ٱلْمَأْوَىٰ نُزُلًۢا بِمَا كَانُوا۟ يَعْمَلُونَ",
      "text_uthmani_tajweed": "أَ<tajweed class=ghunnah>مّ</tajweed>َا <tajweed class=ham_wasl>ٱ</tajweed>لَّذِينَ ءَامَنُو<tajweed class=slnt>اْ</tajweed> وَعَمِلُو<tajweed class=slnt>اْ</tajweed> <tajweed class=ham_wasl>ٱ</tajweed><tajweed class=laam_shamsiyah>ل</tajweed>صَّ<tajweed class=madda_normal>ـٰ</tajweed>لِحَ<tajweed class=madda_normal>ـٰ</tajweed>تِ فَلَهُمْ جَ<tajweed class=ghunnah>نّ</tajweed>َ<tajweed class=madda_normal>ـٰ</tajweed>تُ <tajweed class=ham_wasl>ٱ</tajweed>لْمَأْوَىٰ نُزُل<tajweed class=iqlab>اَۢ ب</tajweed>ِمَا كَانُو<tajweed class=slnt>اْ</tajweed> يَعْمَل<tajweed class=madda_permissible>ُو</tajweed>نَ <span class=end>١٩</span>",
      "page_number": 416,
      "juz_number": 21,
      "audio": {
        "url": "Alafasy/mp3/032019.mp3",
        "segments": [
          [
            0,
            1,
            30,
            1110
          ],
          [
            1,
            2,
            1120,
            2130
          ],
          [
            2,
            3,
            2140,
            3170
          ],
          [
            3,
            4,
            3180,
            3860
          ],
          [
            4,
            5,
            3870,
            5250
          ],
          [
            5,
            6,
            5260,
            6050
          ],
          [
            6,
            7,
            6060,
            7750
          ],
          [
            7,
            8,
            7760,
            8750
          ],
          [
            8,
            9,
            8760,
            11520
          ],
          [
            9,
            10,
            11530,
            12140
          ],
          [
            10,
            11,
            12150,
            12980
          ],
          [
            11,
            12,
            12990,
            15780
          ]
        ]
      },
      "translations": [
        {
          "id": 661465,
          "resource_id": 101,
          "text": "Иймон келтирган ва яхши амаллар қилган зотлар учун қилиб ўтган амаллари сабабли жаннат маъволари манзил бўлур."
        }
      ],
      "audio_url": "https://audio.quran.com/reciters/7/Alafasy/mp3/032019.mp3"
    },
    {
      "id": 3523,
      "verse_number": 20,
      "verse_key": "32:20",
      "hizb_number": 42,
      "rub_el_hizb_number": 166,
      "ruku_number": 361,
      "manzil_number": 5,
      "sajdah_number": null,
      "text_uthmani": "وَأَمَّا ٱلَّذِينَ فَسَقُوا۟ فَمَأْوَىٰهُمُ ٱلنَّارُ ۖ كُلَّمَآ أَرَادُوٓا۟ أَن يَخْرُجُوا۟ مِنْهَآ أُعِيدُوا۟ فِيهَا وَقِيلَ لَهُمْ ذُوقُوا۟ عَذَابَ ٱلنَّارِ ٱلَّذِى كُنتُم بِهِۦ تُكَذِّبُونَ",
      "text_uthmani_tajweed": "وَأَ<tajweed class=ghunnah>مّ</tajweed>َا <tajweed class=ham_wasl>ٱ</tajweed>لَّذِينَ فَسَقُو<tajweed class=slnt>اْ</tajweed> فَمَأْوَ<tajweed class=madda_normal>ٮٰ</tajweed>هُمُ <tajweed class=ham_wasl>ٱ</tajweed><tajweed class=laam_shamsiyah>ل</tajweed><tajweed class=ghunnah>نّ</tajweed>َارُ‌ۖ كُلَّم<tajweed class=madda_obligatory>َآ</tajweed> أَرَاد<tajweed class=madda_obligatory>ُوٓ</tajweed><tajweed class=slnt>اْ</tajweed> أ<tajweed class=idgham_ghunnah>َن ي</tajweed>َخْرُجُو<tajweed class=slnt>اْ</tajweed> مِنْه<tajweed class=madda_obligatory>َآ</tajweed> أُعِيدُو<tajweed class=slnt>اْ</tajweed> فِيهَا وَقِيلَ لَهُمْ ذُوقُو<tajweed class=slnt>اْ</tajweed> عَذَابَ <tajweed class=ham_wasl>ٱ</tajweed><tajweed class=laam_shamsiyah>ل</tajweed><tajweed class=ghunnah>نّ</tajweed>َارِ <tajweed class=ham_wasl>ٱ</tajweed>لَّذِى كُ<tajweed class=ikhafa>نت</tajweed><tajweed class=ikhafa_shafawi>ُم ب</tajweed>ِه<tajweed class=madda_normal>ِۦ</tajweed> تُكَذِّب<tajweed class=madda_permissible>ُو</tajweed>نَ <span class=end>٢٠</span>",
      "page_number": 416,
      "juz_number": 21,
      "audio": {
        "url": "Alafasy/mp3/032020.mp3",
        "segments": [
          [
            0,
            1,
            100,
            1550
          ],
          [
            1,
            2,
            1560,
            2520
          ],
          [
            2,
            3,
            2530,
            3330
          ],
          [
            3,
            4,
            3340,
            4790
          ],
          [
            4,
            5,
            4800,
            8580
          ],
          [
            5,
            6,
            8590,
            10880
          ],
          [
            6,
            7,
            10890,
            13110
          ],
          [
            7,
            8,
            13120,
            14230
          ],
          [
            8,
            9,
            14240,
            15120
          ],
          [
            9,
            10,
            15130,
            15510
          ],
          [
            10,
            11,
            15520,
            18220
          ],
          [
            11,
            12,
            18230,
            19060
          ],
          [
            12,
            13,
            19070,
            19930
          ],
          [
            13,
            14,
            19940,
            22330
          ],
          [
            14,
            15,
            22340,
            23080
          ],
          [
            15,
            16,
            23090,
            23930
          ],
          [
            16,
            17,
            23940,
            25410
          ],
          [
            17,
            18,
            25420,
            26140
          ],
          [
            18,
            19,
            26150,
            28470
          ],
          [
            19,
            20,
            28480,
            29030
          ],
          [
            20,
            21,
            29040,
            32050
          ]
        ]
      },
      "translations": [
        {
          "id": 661466,
          "resource_id": 101,
          "text": "Фосиқ бўлган кимсаларнинг маъволари — борар жйлари эса дўзахдир. Ҳар қачон ундан чиқмоқчи бўлсалар, яна унга қайтарилурлар ва уларга: «Ўзларингиз ёлғон деган дўзах азобини тотингиз», дейилур."
        }
      ],
      "audio_url": "https://audio.quran.com/reciters/7/Alafasy/mp3/032020.mp3"
    },
    {
      "id": 3524,
      "verse_number": 21,
      "verse_key": "32:21",
      "hizb_number": 42,
      "rub_el_hizb_number": 166,
      "ruku_number": 361,
      "manzil_number": 5,
      "sajdah_number": null,
      "text_uthmani": "وَلَنُذِيقَنَّهُم مِّنَ ٱلْعَذَابِ ٱلْأَدْنَىٰ دُونَ ٱلْعَذَابِ ٱلْأَكْبَرِ لَعَلَّهُمْ يَرْجِعُونَ",
      "text_uthmani_tajweed": "وَلَنُذِيقَ<tajweed class=ghunnah>نّ</tajweed>َه<tajweed class=idgham_shafawi>ُم م</tajweed>ِّنَ <tajweed class=ham_wasl>ٱ</tajweed>لْعَذَابِ <tajweed class=ham_wasl>ٱ</tajweed>لْأَ<tajweed class=qalaqah>دْ</tajweed>نَىٰ دُونَ <tajweed class=ham_wasl>ٱ</tajweed>لْعَذَابِ <tajweed class=ham_wasl>ٱ</tajweed>لْأَكْبَرِ لَعَلَّهُمْ يَرْجِع<tajweed class=madda_permissible>ُو</tajweed>نَ <span class=end>٢١</span>",
      "page_number": 417,
      "juz_number": 21,
      "audio": {
        "url": "Alafasy/mp3/032021.mp3",
        "segments": [
          [
            0,
            1,
            50,
            3250
          ],
          [
            1,
            2,
            3260,
            3510
          ],
          [
            2,
            3,
            3520,
            4520
          ],
          [
            3,
            4,
            4530,
            5440
          ],
          [
            4,
            5,
            5450,
            6010
          ],
          [
            5,
            6,
            6020,
            7010
          ],
          [
            6,
            7,
            7020,
            7960
          ],
          [
            7,
            8,
            7970,
            9070
          ],
          [
            8,
            9,
            9080,
            12060
          ]
        ]
      },
      "translations": [
        {
          "id": 661467,
          "resource_id": 101,
          "text": "Албатта Биз улар шояд ўз (куфру исёнларидан) қайтсалар, деб уларга (Қиёмат Кунидаги) улуғ азобдан илгари яқин азобни (яъни, дунё азобини — турли кулфат-балоларни, мусибатларни) тотдирурмиз."
        }
      ],
      "audio_url": "https://audio.quran.com/reciters/7/Alafasy/mp3/032021.mp3"
    },
    {
      "id": 3525,
      "verse_number": 22,
      "verse_key": "32:22",
      "hizb_number": 42,
      "rub_el_hizb_number": 166,
      "ruku_number": 361,
      "manzil_number": 5,
      "sajdah_number": null,
      "text_uthmani": "وَمَنْ أَظْلَمُ مِمَّن ذُكِّرَ بِـَٔايَـٰتِ رَبِّهِۦ ثُمَّ أَعْرَضَ عَنْهَآ ۚ إِنَّا مِنَ ٱلْمُجْرِمِينَ مُنتَقِمُونَ",
      "text_uthmani_tajweed": "وَمَنْ أَظْلَمُ مِ<tajweed class=ghunnah>مّ</tajweed>َ<tajweed class=ikhafa>ن ذ</tajweed>ُكِّرَ بِـَٔـايَ<tajweed class=madda_normal>ـٰ</tajweed>تِ رَبِّه<tajweed class=madda_normal>ِۦ</tajweed> ثُ<tajweed class=ghunnah>مّ</tajweed>َ أَعْرَضَ عَنْه<tajweed class=madda_obligatory>َآ‌ۚ</tajweed> إِ<tajweed class=ghunnah>نّ</tajweed>َا مِنَ <tajweed class=ham_wasl>ٱ</tajweed>لْمُ<tajweed class=qalaqah>جْ</tajweed>رِمِينَ مُ<tajweed class=ikhafa>نت</tajweed>َقِم<tajweed class=madda_permissible>ُو</tajweed>نَ <span class=end>٢٢</span>",
      "page_number": 417,
      "juz_number": 21,
      "audio": {
        "url": "Alafasy/mp3/032022.mp3",
        "segments": [
          [
            0,
            1,
            40,
            650
          ],
          [
            1,
            2,
            660,
            1330
          ],
          [
            2,
            3,
            1340,
            3710
          ],
          [
            3,
            4,
            3720,
            4490
          ],
          [
            4,
            5,
            4500,
            5610
          ],
          [
            5,
            6,
            5620,
            6570
          ],
          [
            6,
            7,
            6580,
            7730
          ],
          [
            7,
            8,
            7740,
            8490
          ],
          [
            8,
            9,
            8500,
            9860
          ],
          [
            9,
            10,
            9870,
            11630
          ],
          [
            10,
            11,
            11640,
            11980
          ],
          [
            11,
            12,
            11990,
            13480
          ],
          [
            12,
            13,
            13490,
            17910
          ]
        ]
      },
      "translations": [
        {
          "id": 661468,
          "resource_id": 101,
          "text": "Ўз Парвардигорининг оятлари билан панд-насиҳат қилинганидан сўнг, улардан юз ўгирган кимсадан ҳам золимроқ ким бор?! Албатта Биз ундай жиноятчи кимсалардан интиқом олгувчидирмиз."
        }
      ],
      "audio_url": "https://audio.quran.com/reciters/7/Alafasy/mp3/032022.mp3"
    },
    {
      "id": 3526,
      "verse_number": 23,
      "verse_key": "32:23",
      "hizb_number": 42,
      "rub_el_hizb_number": 166,
      "ruku_number": 362,
      "manzil_number": 5,
      "sajdah_number": null,
      "text_uthmani": "وَلَقَدْ ءَاتَيْنَا مُوسَى ٱلْكِتَـٰبَ فَلَا تَكُن فِى مِرْيَةٍ مِّن لِّقَآئِهِۦ ۖ وَجَعَلْنَـٰهُ هُدًى لِّبَنِىٓ إِسْرَٰٓءِيلَ",
      "text_uthmani_tajweed": "وَلَقَ<tajweed class=qalaqah>دْ</tajweed> ءَاتَيْنَا مُوسَى <tajweed class=ham_wasl>ٱ</tajweed>لْكِتَ<tajweed class=madda_normal>ـٰ</tajweed>بَ فَلَا تَكُ<tajweed class=ikhafa>ن ف</tajweed>ِى مِرْيَ<tajweed class=idgham_ghunnah>ةٍ م</tajweed>ّ<tajweed class=idgham_wo_ghunnah>ِن ل</tajweed>ِّق<tajweed class=madda_obligatory>َا</tajweed>ٓئِه<tajweed class=madda_normal>ِۦ‌ۖ</tajweed> وَجَعَلْنَ<tajweed class=madda_normal>ـٰ</tajweed>هُ هُ<tajweed class=idgham_wo_ghunnah>دًى ل</tajweed>ِّبَن<tajweed class=madda_obligatory>ِىٓ</tajweed> إِسْر<tajweed class=madda_obligatory>َٲ</tajweed>ٓء<tajweed class=madda_permissible>ِي</tajweed>لَ <span class=end>٢٣</span>",
      "page_number": 417,
      "juz_number": 21,
      "audio": {
        "url": "Alafasy/mp3/032023.mp3",
        "segments": [
          [
            0,
            1,
            120,
            770
          ],
          [
            1,
            2,
            780,
            1920
          ],
          [
            2,
            3,
            1930,
            2430
          ],
          [
            3,
            4,
            2440,
            3350
          ],
          [
            4,
            5,
            3360,
            3870
          ],
          [
            5,
            6,
            3880,
            5170
          ],
          [
            6,
            7,
            5180,
            5600
          ],
          [
            7,
            8,
            5610,
            7570
          ],
          [
            8,
            9,
            7580,
            7700
          ],
          [
            9,
            10,
            7710,
            10640
          ],
          [
            10,
            11,
            10650,
            11950
          ],
          [
            11,
            12,
            11960,
            12230
          ],
          [
            12,
            13,
            12240,
            14210
          ],
          [
            13,
            14,
            14220,
            17850
          ]
        ]
      },
      "translations": [
        {
          "id": 661469,
          "resource_id": 101,
          "text": "Аниқки, Биз Мусога Китоб — Таврот ато этдик. Бас, (эй Муҳаммад алайҳис-салоту вас-салом), сиз унинг (Тавротга) рўбарў бўлганидан шубҳа-гумонда бўлманг. Биз (Тавротни) Бани Исроил (қавми) учун раҳбар-йўлбошчи қилдик."
        }
      ],
      "audio_url": "https://audio.quran.com/reciters/7/Alafasy/mp3/032023.mp3"
    },
    {
      "id": 3527,
      "verse_number": 24,
      "verse_key": "32:24",
      "hizb_number": 42,
      "rub_el_hizb_number": 166,
      "ruku_number": 362,
      "manzil_number": 5,
      "sajdah_number": null,
      "text_uthmani": "وَجَعَلْنَا مِنْهُمْ أَئِمَّةً يَهْدُونَ بِأَمْرِنَا لَمَّا صَبَرُوا۟ ۖ وَكَانُوا۟ بِـَٔايَـٰتِنَا يُوقِنُونَ",
      "text_uthmani_tajweed": "وَجَعَلْنَا مِنْهُمْ أَئِ<tajweed class=ghunnah>مّ</tajweed>َ<tajweed class=idgham_ghunnah>ةً ي</tajweed>َهْدُونَ بِأَمْرِنَا لَ<tajweed class=ghunnah>مّ</tajweed>َا صَبَرُو<tajweed class=slnt>اْ‌ۖ</tajweed> وَكَانُو<tajweed class=slnt>اْ</tajweed> بِـَٔـايَ<tajweed class=madda_normal>ـٰ</tajweed>تِنَا يُوقِن<tajweed class=madda_permissible>ُو</tajweed>نَ <span class=end>٢٤</span>",
      "page_number": 417,
      "juz_number": 21,
      "audio": {
        "url": "Alafasy/mp3/032024.mp3",
        "segments": [
          [
            0,
            1,
            40,
            1190
          ],
          [
            1,
            2,
            1200,
            1900
          ],
          [
            2,
            3,
            1910,
            4190
          ],
          [
            3,
            4,
            4200,
            5100
          ],
          [
            4,
            5,
            5110,
            6190
          ],
          [
            5,
            6,
            6200,
            7410
          ],
          [
            6,
            7,
            7420,
            8670
          ],
          [
            7,
            8,
            8680,
            9560
          ],
          [
            8,
            9,
            9570,
            11130
          ],
          [
            9,
            10,
            11140,
            13520
          ]
        ]
      },
      "translations": [
        {
          "id": 661470,
          "resource_id": 101,
          "text": "Улар (ўз динлари йўлидаги бало-кулфатларга) сабр-тоқат қилишгач, Биз улардан (одамларни) ҳидоят қиладиган пешволарни чиқардик. Улар Бизнинг оятларимизга аниқ ишонар эдилар."
        }
      ],
      "audio_url": "https://audio.quran.com/reciters/7/Alafasy/mp3/032024.mp3"
    },
    {
      "id": 3528,
      "verse_number": 25,
      "verse_key": "32:25",
      "hizb_number": 42,
      "rub_el_hizb_number": 166,
      "ruku_number": 362,
      "manzil_number": 5,
      "sajdah_number": null,
      "text_uthmani": "إِنَّ رَبَّكَ هُوَ يَفْصِلُ بَيْنَهُمْ يَوْمَ ٱلْقِيَـٰمَةِ فِيمَا كَانُوا۟ فِيهِ يَخْتَلِفُونَ",
      "text_uthmani_tajweed": "إِ<tajweed class=ghunnah>نّ</tajweed>َ رَبَّكَ هُوَ يَفْصِلُ بَيْنَهُمْ يَوْمَ <tajweed class=ham_wasl>ٱ</tajweed>لْقِيَ<tajweed class=madda_normal>ـٰ</tajweed>مَةِ فِيمَا كَانُو<tajweed class=slnt>اْ</tajweed> فِيهِ يَخْتَلِف<tajweed class=madda_permissible>ُو</tajweed>نَ <span class=end>٢٥</span>",
      "page_number": 417,
      "juz_number": 21,
      "audio": {
        "url": "Alafasy/mp3/032025.mp3",
        "segments": [
          [
            0,
            1,
            50,
            1030
          ],
          [
            1,
            2,
            1040,
            1770
          ],
          [
            2,
            3,
            1780,
            2170
          ],
          [
            3,
            4,
            2180,
            2900
          ],
          [
            4,
            5,
            2910,
            3870
          ],
          [
            5,
            6,
            3880,
            4400
          ],
          [
            6,
            7,
            4410,
            5500
          ],
          [
            7,
            8,
            5510,
            6240
          ],
          [
            8,
            9,
            6250,
            7030
          ],
          [
            9,
            10,
            7040,
            7640
          ],
          [
            10,
            11,
            7650,
            9930
          ]
        ]
      },
      "translations": [
        {
          "id": 661471,
          "resource_id": 101,
          "text": "(Эй Муҳаммад алайҳис-салоту вас-салом), албатта Парвардигорингизнинг Ўзи Қиёмат Кунида (одамлар) ўртасида улар ихтилоф қилиб ўтган нарсалар ҳақида Ўз ҳукмини баён қилур."
        }
      ],
      "audio_url": "https://audio.quran.com/reciters/7/Alafasy/mp3/032025.mp3"
    },
    {
      "id": 3529,
      "verse_number": 26,
      "verse_key": "32:26",
      "hizb_number": 42,
      "rub_el_hizb_number": 166,
      "ruku_number": 362,
      "manzil_number": 5,
      "sajdah_number": null,
      "text_uthmani": "أَوَلَمْ يَهْدِ لَهُمْ كَمْ أَهْلَكْنَا مِن قَبْلِهِم مِّنَ ٱلْقُرُونِ يَمْشُونَ فِى مَسَـٰكِنِهِمْ ۚ إِنَّ فِى ذَٰلِكَ لَـَٔايَـٰتٍ ۖ أَفَلَا يَسْمَعُونَ",
      "text_uthmani_tajweed": "أَوَلَمْ يَهْدِ لَهُمْ كَمْ أَهْلَكْنَا مِ<tajweed class=ikhafa>ن ق</tajweed>َ<tajweed class=qalaqah>بْ</tajweed>لِه<tajweed class=idgham_shafawi>ِم م</tajweed>ِّنَ <tajweed class=ham_wasl>ٱ</tajweed>لْقُرُونِ يَمْشُونَ فِى مَسَ<tajweed class=madda_normal>ـٰ</tajweed>كِنِهِمْ‌ۚ إِ<tajweed class=ghunnah>نّ</tajweed>َ فِى ذ<tajweed class=madda_normal>َٲ</tajweed>لِكَ لَأَيَ<tajweed class=madda_normal>ـٰ</tajweed>تٍ‌ۖ أَفَلَا يَسْمَع<tajweed class=madda_permissible>ُو</tajweed>نَ <span class=end>٢٦</span>",
      "page_number": 417,
      "juz_number": 21,
      "audio": {
        "url": "Alafasy/mp3/032026.mp3",
        "segments": [
          [
            0,
            1,
            30,
            660
          ],
          [
            1,
            2,
            670,
            1260
          ],
          [
            2,
            3,
            1270,
            1770
          ],
          [
            3,
            4,
            1780,
            2200
          ],
          [
            4,
            5,
            2210,
            3310
          ],
          [
            5,
            6,
            3320,
            4220
          ],
          [
            6,
            7,
            4230,
            6090
          ],
          [
            7,
            8,
            6100,
            6350
          ],
          [
            8,
            9,
            6360,
            7330
          ],
          [
            9,
            10,
            7340,
            8220
          ],
          [
            10,
            11,
            8230,
            8650
          ],
          [
            11,
            12,
            8660,
            10360
          ],
          [
            12,
            13,
            10370,
            11510
          ],
          [
            13,
            14,
            11520,
            11930
          ],
          [
            14,
            15,
            11940,
            12710
          ],
          [
            15,
            16,
            12720,
            15530
          ],
          [
            16,
            17,
            15540,
            16250
          ],
          [
            17,
            18,
            16260,
            18930
          ]
        ]
      },
      "translations": [
        {
          "id": 661472,
          "resource_id": 101,
          "text": "Ахир уларга (яъни, мушрикларга) Биз улардан илгари қанча аср-авлодларни ҳалок қилганимиз ва ўзлари ўшаларнинг масканларида юрганлари маълум эмасми?! Албатта бунда оят-ибратлар бор-ку! Ахир улар англамайдиларми?!"
        }
      ],
      "audio_url": "https://audio.quran.com/reciters/7/Alafasy/mp3/032026.mp3"
    },
    {
      "id": 3530,
      "verse_number": 27,
      "verse_key": "32:27",
      "hizb_number": 42,
      "rub_el_hizb_number": 166,
      "ruku_number": 362,
      "manzil_number": 5,
      "sajdah_number": null,
      "text_uthmani": "أَوَلَمْ يَرَوْا۟ أَنَّا نَسُوقُ ٱلْمَآءَ إِلَى ٱلْأَرْضِ ٱلْجُرُزِ فَنُخْرِجُ بِهِۦ زَرْعًا تَأْكُلُ مِنْهُ أَنْعَـٰمُهُمْ وَأَنفُسُهُمْ ۖ أَفَلَا يُبْصِرُونَ",
      "text_uthmani_tajweed": "أَوَلَمْ يَرَوْ<tajweed class=slnt>اْ</tajweed> أَ<tajweed class=ghunnah>نّ</tajweed>َا نَسُوقُ <tajweed class=ham_wasl>ٱ</tajweed>لْم<tajweed class=madda_obligatory>َا</tajweed>ٓءَ إِلَى <tajweed class=ham_wasl>ٱ</tajweed>لْأَرْضِ <tajweed class=ham_wasl>ٱ</tajweed>لْجُرُزِ فَنُخْرِجُ بِه<tajweed class=madda_normal>ِۦ</tajweed> زَرْ<tajweed class=ikhafa>عًا ت</tajweed>َأْكُلُ مِنْهُ أَنْعَ<tajweed class=madda_normal>ـٰ</tajweed>مُهُمْ وَأَ<tajweed class=ikhafa>نف</tajweed>ُسُهُمْ‌ۖ أَفَلَا يُ<tajweed class=qalaqah>بْ</tajweed>صِر<tajweed class=madda_permissible>ُو</tajweed>نَ <span class=end>٢٧</span>",
      "page_number": 417,
      "juz_number": 21,
      "audio": {
        "url": "Alafasy/mp3/032027.mp3",
        "segments": [
          [
            0,
            1,
            30,
            660
          ],
          [
            1,
            2,
            670,
            1300
          ],
          [
            2,
            3,
            1310,
            2640
          ],
          [
            3,
            4,
            2650,
            3420
          ],
          [
            4,
            5,
            3430,
            5220
          ],
          [
            5,
            6,
            5230,
            5570
          ],
          [
            6,
            7,
            5580,
            6350
          ],
          [
            7,
            8,
            6360,
            7040
          ],
          [
            8,
            9,
            7050,
            7950
          ],
          [
            9,
            10,
            7960,
            8480
          ],
          [
            10,
            11,
            8490,
            12830
          ],
          [
            11,
            12,
            12840,
            13570
          ],
          [
            12,
            13,
            13580,
            14140
          ],
          [
            13,
            14,
            14150,
            15410
          ],
          [
            14,
            15,
            15420,
            17800
          ],
          [
            15,
            16,
            17810,
            18540
          ],
          [
            16,
            17,
            18550,
            21220
          ]
        ]
      },
      "translations": [
        {
          "id": 661473,
          "resource_id": 101,
          "text": "Ахир улар Биз қуруқ ерга сув ҳайдаб, унинг ёрдамида уларнинг чорвалари ҳам, ўзлари ҳам ейдиган экинларни чиқаришимизни кўрмадиларми?! Ахир қарамайдиларми?!"
        }
      ],
      "audio_url": "https://audio.quran.com/reciters/7/Alafasy/mp3/032027.mp3"
    },
    {
      "id": 3531,
      "verse_number": 28,
      "verse_key": "32:28",
      "hizb_number": 42,
      "rub_el_hizb_number": 166,
      "ruku_number": 362,
      "manzil_number": 5,
      "sajdah_number": null,
      "text_uthmani": "وَيَقُولُونَ مَتَىٰ هَـٰذَا ٱلْفَتْحُ إِن كُنتُمْ صَـٰدِقِينَ",
      "text_uthmani_tajweed": "وَيَقُولُونَ مَتَىٰ هَ<tajweed class=madda_normal>ـٰ</tajweed>ذَا <tajweed class=ham_wasl>ٱ</tajweed>لْفَتْحُ إِ<tajweed class=ikhafa>ن ك</tajweed>ُ<tajweed class=ikhafa>نت</tajweed>ُمْ صَ<tajweed class=madda_normal>ـٰ</tajweed>دِق<tajweed class=madda_permissible>ِي</tajweed>نَ <span class=end>٢٨</span>",
      "page_number": 417,
      "juz_number": 21,
      "audio": {
        "url": "Alafasy/mp3/032028.mp3",
        "segments": [
          [
            0,
            1,
            30,
            1290
          ],
          [
            1,
            2,
            1300,
            1870
          ],
          [
            2,
            3,
            1880,
            2400
          ],
          [
            3,
            4,
            2410,
            3110
          ],
          [
            4,
            5,
            3120,
            4040
          ],
          [
            5,
            6,
            4050,
            5470
          ],
          [
            6,
            7,
            5480,
            8160
          ]
        ]
      },
      "translations": [
        {
          "id": 661474,
          "resource_id": 101,
          "text": "Улар (мусулмонларга): «Агар ростгўй бўлсангизлар қачон мана шу фатҳ (яъни, сизларнинг ғалабангиз) рўй берур», дерлар."
        }
      ],
      "audio_url": "https://audio.quran.com/reciters/7/Alafasy/mp3/032028.mp3"
    },
    {
      "id": 3532,
      "verse_number": 29,
      "verse_key": "32:29",
      "hizb_number": 42,
      "rub_el_hizb_number": 166,
      "ruku_number": 362,
      "manzil_number": 5,
      "sajdah_number": null,
      "text_uthmani": "قُلْ يَوْمَ ٱلْفَتْحِ لَا يَنفَعُ ٱلَّذِينَ كَفَرُوٓا۟ إِيمَـٰنُهُمْ وَلَا هُمْ يُنظَرُونَ",
      "text_uthmani_tajweed": "قُلْ يَوْمَ <tajweed class=ham_wasl>ٱ</tajweed>لْفَتْحِ لَا يَ<tajweed class=ikhafa>نف</tajweed>َعُ <tajweed class=ham_wasl>ٱ</tajweed>لَّذِينَ كَفَر<tajweed class=madda_obligatory>ُوٓ</tajweed><tajweed class=slnt>اْ</tajweed> إِيمَ<tajweed class=madda_normal>ـٰ</tajweed>نُهُمْ وَلَا هُمْ يُ<tajweed class=ikhafa>نظ</tajweed>َر<tajweed class=madda_permissible>ُو</tajweed>نَ <span class=end>٢٩</span>",
      "page_number": 417,
      "juz_number": 21,
      "audio": {
        "url": "Alafasy/mp3/032029.mp3",
        "segments": [
          [
            0,
            1,
            40,
            230
          ],
          [
            1,
            2,
            240,
            890
          ],
          [
            2,
            3,
            900,
            1640
          ],
          [
            3,
            4,
            1650,
            1990
          ],
          [
            4,
            5,
            2000,
            3390
          ],
          [
            5,
            6,
            3400,
            4290
          ],
          [
            6,
            7,
            4300,
            6120
          ],
          [
            7,
            8,
            6130,
            7360
          ],
          [
            8,
            9,
            7370,
            7940
          ],
          [
            9,
            10,
            7950,
            8320
          ],
          [
            10,
            11,
            8330,
            9220
          ]
        ]
      },
      "translations": [
        {
          "id": 661475,
          "resource_id": 101,
          "text": "(Эй Муҳаммад алайҳис-салоту вас-салом), айтинг: «Фатҳ кунида кофир бўлган кимсаларга иймон келтиришлари фойда бермай қолур ва уларга (тавба-тазарруъ қилиш учун муҳлат ҳам берилмас."
        }
      ],
      "audio_url": "https://audio.quran.com/reciters/7/Alafasy/mp3/032029.mp3"
    },
    {
      "id": 3533,
      "verse_number": 30,
      "verse_key": "32:30",
      "hizb_number": 42,
      "rub_el_hizb_number": 166,
      "ruku_number": 362,
      "manzil_number": 5,
      "sajdah_number": null,
      "text_uthmani": "فَأَعْرِضْ عَنْهُمْ وَٱنتَظِرْ إِنَّهُم مُّنتَظِرُونَ",
      "text_uthmani_tajweed": "فَأَعْرِضْ عَنْهُمْ وَ<tajweed class=ham_wasl>ٱ</tajweed><tajweed class=ikhafa>نت</tajweed>َظِرْ إِ<tajweed class=ghunnah>نّ</tajweed>َه<tajweed class=idgham_shafawi>ُم م</tajweed>ُّ<tajweed class=ikhafa>نت</tajweed>َظِر<tajweed class=madda_permissible>ُو</tajweed>نَ <span class=end>٣٠</span>",
      "page_number": 417,
      "juz_number": 21,
      "audio": {
        "url": "Alafasy/mp3/032030.mp3",
        "segments": [
          [
            0,
            1,
            50,
            960
          ],
          [
            1,
            2,
            970,
            1800
          ],
          [
            2,
            3,
            1810,
            3230
          ],
          [
            3,
            4,
            3240,
            5520
          ],
          [
            4,
            5,
            5530,
            9540
          ]
        ]
      },
      "translations": [
        {
          "id": 661476,
          "resource_id": 101,
          "text": "Сўнг сиз улардан юз ўгиринг ва (уларга келадиган азобга) кўз тутинг! Зеро, улар ҳам кўз тутгувчидирлар."
        }
      ],
      "audio_url": "https://audio.quran.com/reciters/7/Alafasy/mp3/032030.mp3"
    }
  ]
}
