{
  "verses": [
    {
      "id": 4785,
      "verse_number": 1,
      "verse_key": "53:1",
      "hizb_number": 53,
      "rub_el_hizb_number": 210,
      "ruku_number": 462,
      "manzil_number": 7,
      "sajdah_number": null,
      "text_uthmani": " وَٱلنَّجْمِ إِذَا هَوَىٰ",
      "text_uthmani_tajweed": "وَ<tajweed class=ham_wasl>ٱ</tajweed><tajweed class=laam_shamsiyah>ل</tajweed><tajweed class=ghunnah>نّ</tajweed>َ<tajweed class=qalaqah>جْ</tajweed>مِ إِذَا هَوَىٰ <span class=end>١</span>",
      "page_number": 526,
      "juz_number": 27,
      "audio": {
        "url": "Alafasy/mp3/053001.mp3",
        "segments": [
          [
            0,
            1,
            30,
            2280
          ],
          [
            1,
            2,
            2290,
            2970
          ],
          [
            2,
            3,
            2980,
            3980
          ]
        ]
      },
      "translations": [
        {
          "id": 662728,
          "resource_id": 101,
          "text": "Ботиб кетаётган юлдузга қасамки,"
        }
      ],
      "audio_url": "https://audio.quran.com/reciters/7/Alafasy/mp3/053001.mp3"
    },
    {
      "id": 4786,
      "verse_number": 2,
      "verse_key": "53:2",
      "hizb_number": 53,
      "rub_el_hizb_number": 210,
      "ruku_number": 462,
      "manzil_number": 7,
      "sajdah_number": null,
      "text_uthmani": "مَا ضَلَّ صَاحِبُكُمْ وَمَا غَوَىٰ",
      "text_uthmani_tajweed": "مَا ضَلَّ صَاحِبُكُمْ وَمَا غَوَىٰ <span class=end>٢</span>",
      "page_number": 526,
      "juz_number": 27,
      "audio": {
        "url": "Alafasy/mp3/053002.mp3",
        "segments": [
          [
            0,
            1,
            30,
            410
          ],
          [
            1,
            2,
            420,
            1120
          ],
          [
            2,
            3,
            1130,
            2560
          ],
          [
            3,
            4,
            2570,
            3200
          ],
          [
            4,
            5,
            3210,
            4280
          ]
        ]
      },
      "translations": [
        {
          "id": 662729,
          "resource_id": 101,
          "text": "Сизларнинг соҳибингиз (яъни, Муҳаммад алайҳис-салоту вас-салом) залолатга ҳам кетгани йўқ, йўлдан ҳам озгани йўқ!"
        }
      ],
      "audio_url": "https://audio.quran.com/reciters/7/Alafasy/mp3/053002.mp3"
    },
    {
      "id": 4787,
      "verse_number": 3,
      "verse_key": "53:3",
      "hizb_number": 53,
      "rub_el_hizb_number": 210,
      "ruku_number": 462,
      "manzil_number": 7,
      "sajdah_number": null,
      "text_uthmani": "وَمَا يَنطِقُ عَنِ ٱلْهَوَىٰٓ",
      "text_uthmani_tajweed": "وَمَا يَ<tajweed class=ikhafa>نط</tajweed>ِقُ عَنِ <tajweed class=ham_wasl>ٱ</tajweed>لْهَوَىٰٓ <span class=end>٣</span>",
      "page_number": 526,
      "juz_number": 27,
      "audio": {
        "url": "Alafasy/mp3/053003.mp3",
        "segments": [
          [
            0,
            1,
            30,
            640
          ],
          [
            1,
            2,
            650,
            2400
          ],
          [
            2,
            3,
            2410,
            2890
          ],
          [
            3,
            4,
            2900,
            4320
          ]
        ]
      },
      "translations": [
        {
          "id": 662730,
          "resource_id": 101,
          "text": "Ва у (сизларга келтираётган Қуръонни) ўз ҳавойи-хоҳиши билан сўзламас."
        }
      ],
      "audio_url": "https://audio.quran.com/reciters/7/Alafasy/mp3/053003.mp3"
    },
    {
      "id": 4788,
      "verse_number": 4,
      "verse_key": "53:4",
      "hizb_number": 53,
      "rub_el_hizb_number": 210,
      "ruku_number": 462,
      "manzil_number": 7,
      "sajdah_number": null,
      "text_uthmani": "إِنْ هُوَ إِلَّا وَحْىٌ يُوحَىٰ",
      "text_uthmani_tajweed": "إِنْ هُوَ إِلَّا وَحْ<tajweed class=idgham_ghunnah>ىٌ ي</tajweed>ُوحَىٰ <span class=end>٤</span>",
      "page_number": 526,
      "juz_number": 27,
      "audio": {
        "url": "Alafasy/mp3/053004.mp3",
        "segments": [
          [
            0,
            1,
            30,
            420
          ],
          [
            1,
            2,
            430,
            860
          ],
          [
            2,
            3,
            870,
            1760
          ],
          [
            3,
            4,
            1770,
            3280
          ],
          [
            4,
            5,
            3290,
            4490
          ]
        ]
      },
      "translations": [
        {
          "id": 662731,
          "resource_id": 101,
          "text": "У (Қуръон) фақат (Аллоҳ томонидан пайғамбарга) ваҳий қилинаётган (туширилаётган) бир ваҳийдир."
        }
      ],
      "audio_url": "https://audio.quran.com/reciters/7/Alafasy/mp3/053004.mp3"
    },
    {
      "id": 4789,
      "verse_number": 5,
      "verse_key": "53:5",
      "hizb_number": 53,
      "rub_el_hizb_number": 210,
      "ruku_number": 462,
      "manzil_number": 7,
      "sajdah_number": null,
      "text_uthmani": "عَلَّمَهُۥ شَدِيدُ ٱلْقُوَىٰ",
      "text_uthmani_tajweed": "عَلَّمَهُ<tajweed class=madda_normal>ۥ</tajweed> شَدِيدُ <tajweed class=ham_wasl>ٱ</tajweed>لْقُوَىٰ <span class=end>٥</span>",
      "page_number": 526,
      "juz_number": 27,
      "audio": {
        "url": "Alafasy/mp3/053005.mp3",
        "segments": [
          [
            0,
            1,
            30,
            1290
          ],
          [
            1,
            2,
            1300,
            2270
          ],
          [
            2,
            3,
            2280,
            3670
          ]
        ]
      },
      "translations": [
        {
          "id": 662732,
          "resource_id": 101,
          "text": "Унга (бу ваҳийни) бир кучга тўлган зот (яъни, Жаброил алайҳиссалом) таълим бермишдир."
        }
      ],
      "audio_url": "https://audio.quran.com/reciters/7/Alafasy/mp3/053005.mp3"
    },
    {
      "id": 4790,
      "verse_number": 6,
      "verse_key": "53:6",
      "hizb_number": 53,
      "rub_el_hizb_number": 210,
      "ruku_number": 462,
      "manzil_number": 7,
      "sajdah_number": null,
      "text_uthmani": "ذُو مِرَّةٍ فَٱسْتَوَىٰ",
      "text_uthmani_tajweed": "ذُو مِرَّ<tajweed class=ikhafa>ةٍ ف</tajweed>َ<tajweed class=ham_wasl>ٱ</tajweed>سْتَوَىٰ <span class=end>٦</span>",
      "page_number": 526,
      "juz_number": 27,
      "audio": {
        "url": "Alafasy/mp3/053006.mp3",
        "segments": [
          [
            0,
            1,
            40,
            530
          ],
          [
            1,
            2,
            540,
            2420
          ],
          [
            2,
            3,
            2430,
            3920
          ]
        ]
      },
      "translations": [
        {
          "id": 662733,
          "resource_id": 101,
          "text": "Соҳиби қудрат (яъни, Жаброил алайҳиссалом таълим бермишдир)."
        }
      ],
      "audio_url": "https://audio.quran.com/reciters/7/Alafasy/mp3/053006.mp3"
    },
    {
      "id": 4791,
      "verse_number": 7,
      "verse_key": "53:7",
      "hizb_number": 53,
      "rub_el_hizb_number": 210,
      "ruku_number": 462,
      "manzil_number": 7,
      "sajdah_number": null,
      "text_uthmani": "وَهُوَ بِٱلْأُفُقِ ٱلْأَعْلَىٰ",
      "text_uthmani_tajweed": "وَهُوَ بِ<tajweed class=ham_wasl>ٱ</tajweed>لْأُفُقِ <tajweed class=ham_wasl>ٱ</tajweed>لْأَعْلَىٰ <span class=end>٧</span>",
      "page_number": 526,
      "juz_number": 27,
      "audio": {
        "url": "Alafasy/mp3/053007.mp3",
        "segments": [
          [
            0,
            1,
            30,
            670
          ],
          [
            1,
            2,
            680,
            1860
          ],
          [
            2,
            3,
            1870,
            3390
          ]
        ]
      },
      "translations": [
        {
          "id": 662734,
          "resource_id": 101,
          "text": "Бас, у (аввал) юксак уфқда (кўриниб), тик турди."
        }
      ],
      "audio_url": "https://audio.quran.com/reciters/7/Alafasy/mp3/053007.mp3"
    },
    {
      "id": 4792,
      "verse_number": 8,
      "verse_key": "53:8",
      "hizb_number": 53,
      "rub_el_hizb_number": 210,
      "ruku_number": 462,
      "manzil_number": 7,
      "sajdah_number": null,
      "text_uthmani": "ثُمَّ دَنَا فَتَدَلَّىٰ",
      "text_uthmani_tajweed": "ثُ<tajweed class=ghunnah>مّ</tajweed>َ دَنَا فَتَدَلَّىٰ <span class=end>٨</span>",
      "page_number": 526,
      "juz_number": 27,
      "audio": {
        "url": "Alafasy/mp3/053008.mp3",
        "segments": [
          [
            0,
            1,
            30,
            1240
          ],
          [
            1,
            2,
            1250,
            1950
          ],
          [
            2,
            3,
            1960,
            3620
          ]
        ]
      },
      "translations": [
        {
          "id": 662735,
          "resource_id": 101,
          "text": "Сўнгра яқинлашиб, пастлади."
        }
      ],
      "audio_url": "https://audio.quran.com/reciters/7/Alafasy/mp3/053008.mp3"
    },
    {
      "id": 4793,
      "verse_number": 9,
      "verse_key": "53:9",
      "hizb_number": 53,
      "rub_el_hizb_number": 210,
      "ruku_number": 462,
      "manzil_number": 7,
      "sajdah_number": null,
      "text_uthmani": "فَكَانَ قَابَ قَوْسَيْنِ أَوْ أَدْنَىٰ",
      "text_uthmani_tajweed": "فَكَانَ قَابَ قَوْسَيْنِ أَوْ أَ<tajweed class=qalaqah>دْ</tajweed>نَىٰ <span class=end>٩</span>",
      "page_number": 526,
      "juz_number": 27,
      "audio": {
        "url": "Alafasy/mp3/053009.mp3",
        "segments": [
          [
            0,
            1,
            30,
            890
          ],
          [
            1,
            2,
            900,
            1580
          ],
          [
            2,
            3,
            1590,
            2790
          ],
          [
            3,
            4,
            2800,
            3230
          ],
          [
            4,
            5,
            3240,
            4290
          ]
        ]
      },
      "translations": [
        {
          "id": 662736,
          "resource_id": 101,
          "text": "Бас, (Муҳаммад алайҳис-салоту вас-саломга) икки камон оралиғида ё (ундан-да) яқинроқ бўлиб;"
        }
      ],
      "audio_url": "https://audio.quran.com/reciters/7/Alafasy/mp3/053009.mp3"
    },
    {
      "id": 4794,
      "verse_number": 10,
      "verse_key": "53:10",
      "hizb_number": 53,
      "rub_el_hizb_number": 210,
      "ruku_number": 462,
      "manzil_number": 7,
      "sajdah_number": null,
      "text_uthmani": "فَأَوْحَىٰٓ إِلَىٰ عَبْدِهِۦ مَآ أَوْحَىٰ",
      "text_uthmani_tajweed": "فَأَوْحَ<tajweed class=madda_obligatory>ىٰٓ</tajweed> إِلَىٰ عَ<tajweed class=qalaqah>بْ</tajweed>دِه<tajweed class=madda_normal>ِۦ</tajweed> م<tajweed class=madda_obligatory>َآ</tajweed> أَوْحَىٰ <span class=end>١٠</span>",
      "page_number": 526,
      "juz_number": 27,
      "audio": {
        "url": "Alafasy/mp3/053010.mp3",
        "segments": [
          [
            0,
            1,
            30,
            2480
          ],
          [
            1,
            2,
            2490,
            3080
          ],
          [
            2,
            3,
            3090,
            4310
          ],
          [
            3,
            4,
            4320,
            5930
          ],
          [
            4,
            5,
            5940,
            7220
          ]
        ]
      },
      "translations": [
        {
          "id": 662737,
          "resource_id": 101,
          "text": "(Аллоҳ) ўз бандаси (Муҳаммад алайҳис-салоту вас-салом)га туширган ваҳийни келтиради."
        }
      ],
      "audio_url": "https://audio.quran.com/reciters/7/Alafasy/mp3/053010.mp3"
    },
    {
      "id": 4795,
      "verse_number": 11,
      "verse_key": "53:11",
      "hizb_number": 53,
      "rub_el_hizb_number": 210,
      "ruku_number": 462,
      "manzil_number": 7,
      "sajdah_number": null,
      "text_uthmani": "مَا كَذَبَ ٱلْفُؤَادُ مَا رَأَىٰٓ",
      "text_uthmani_tajweed": "مَا كَذَبَ <tajweed class=ham_wasl>ٱ</tajweed>لْفُؤَادُ مَا رَأَىٰٓ <span class=end>١١</span>",
      "page_number": 526,
      "juz_number": 27,
      "audio": {
        "url": "Alafasy/mp3/053011.mp3",
        "segments": [
          [
            0,
            1,
            60,
            460
          ],
          [
            1,
            2,
            470,
            1160
          ],
          [
            2,
            3,
            1170,
            2330
          ],
          [
            3,
            4,
            2340,
            2700
          ],
          [
            4,
            5,
            2710,
            3510
          ]
        ]
      },
      "translations": [
        {
          "id": 662738,
          "resource_id": 101,
          "text": "(Пайғамбарнинг) кўнгли кўрган нарсасини инкор этмади. (Яъни, Жаброил фариштанинг суратини кўриб, пайғамбарнинг кўнгли ҳам қаноатланди ва унинг Аллоҳ таоло томонидаи фаришта эканлигига иймон келтирди)."
        }
      ],
      "audio_url": "https://audio.quran.com/reciters/7/Alafasy/mp3/053011.mp3"
    },
    {
      "id": 4796,
      "verse_number": 12,
      "verse_key": "53:12",
      "hizb_number": 53,
      "rub_el_hizb_number": 210,
      "ruku_number": 462,
      "manzil_number": 7,
      "sajdah_number": null,
      "text_uthmani": "أَفَتُمَـٰرُونَهُۥ عَلَىٰ مَا يَرَىٰ",
      "text_uthmani_tajweed": "أَفَتُمَ<tajweed class=madda_normal>ـٰ</tajweed>رُونَهُ<tajweed class=madda_normal>ۥ</tajweed> عَلَىٰ مَا يَرَىٰ <span class=end>١٢</span>",
      "page_number": 526,
      "juz_number": 27,
      "audio": {
        "url": "Alafasy/mp3/053012.mp3",
        "segments": [
          [
            0,
            1,
            70,
            2250
          ],
          [
            1,
            2,
            2260,
            3060
          ],
          [
            2,
            3,
            3070,
            3500
          ],
          [
            3,
            4,
            3510,
            4530
          ]
        ]
      },
      "translations": [
        {
          "id": 662739,
          "resource_id": 101,
          "text": "Энди сизлар, (эй мушриклар, пайғамбар) кўриб турган нарсаси устида у билан тортишурмисизлар?!"
        }
      ],
      "audio_url": "https://audio.quran.com/reciters/7/Alafasy/mp3/053012.mp3"
    },
    {
      "id": 4797,
      "verse_number": 13,
      "verse_key": "53:13",
      "hizb_number": 53,
      "rub_el_hizb_number": 210,
      "ruku_number": 462,
      "manzil_number": 7,
      "sajdah_number": null,
      "text_uthmani": "وَلَقَدْ رَءَاهُ نَزْلَةً أُخْرَىٰ",
      "text_uthmani_tajweed": "وَلَقَ<tajweed class=qalaqah>دْ</tajweed> رَءَاهُ نَزْلَةً أُخْرَىٰ <span class=end>١٣</span>",
      "page_number": 526,
      "juz_number": 27,
      "audio": {
        "url": "Alafasy/mp3/053013.mp3",
        "segments": [
          [
            0,
            1,
            40,
            820
          ],
          [
            1,
            2,
            830,
            1800
          ],
          [
            2,
            3,
            1810,
            2930
          ],
          [
            3,
            4,
            2940,
            4140
          ]
        ]
      },
      "translations": [
        {
          "id": 662740,
          "resource_id": 101,
          "text": "Қасамки, (Муҳаммад алайҳис-салоту вас-салом Жаброил фариштани ўзининг аслий суратида) иккинчи бор кўрди."
        }
      ],
      "audio_url": "https://audio.quran.com/reciters/7/Alafasy/mp3/053013.mp3"
    },
    {
      "id": 4798,
      "verse_number": 14,
      "verse_key": "53:14",
      "hizb_number": 53,
      "rub_el_hizb_number": 210,
      "ruku_number": 462,
      "manzil_number": 7,
      "sajdah_number": null,
      "text_uthmani": "عِندَ سِدْرَةِ ٱلْمُنتَهَىٰ",
      "text_uthmani_tajweed": "عِ<tajweed class=ikhafa>ند</tajweed>َ سِ<tajweed class=qalaqah>دْ</tajweed>رَةِ <tajweed class=ham_wasl>ٱ</tajweed>لْمُ<tajweed class=ikhafa>نت</tajweed>َهَىٰ <span class=end>١٤</span>",
      "page_number": 526,
      "juz_number": 27,
      "audio": {
        "url": "Alafasy/mp3/053014.mp3",
        "segments": [
          [
            0,
            1,
            80,
            1370
          ],
          [
            1,
            2,
            1380,
            2360
          ],
          [
            2,
            3,
            2370,
            4830
          ]
        ]
      },
      "translations": [
        {
          "id": 662741,
          "resource_id": 101,
          "text": "(Жаннат) четидаги Нилуфар олдида (кўрди). <sup foot_note=145270>1</sup>"
        }
      ],
      "audio_url": "https://audio.quran.com/reciters/7/Alafasy/mp3/053014.mp3"
    },
    {
      "id": 4799,
      "verse_number": 15,
      "verse_key": "53:15",
      "hizb_number": 53,
      "rub_el_hizb_number": 210,
      "ruku_number": 462,
      "manzil_number": 7,
      "sajdah_number": null,
      "text_uthmani": "عِندَهَا جَنَّةُ ٱلْمَأْوَىٰٓ",
      "text_uthmani_tajweed": "عِ<tajweed class=ikhafa>ند</tajweed>َهَا جَ<tajweed class=ghunnah>نّ</tajweed>َةُ <tajweed class=ham_wasl>ٱ</tajweed>لْمَأْوَىٰٓ <span class=end>١٥</span>",
      "page_number": 526,
      "juz_number": 27,
      "audio": {
        "url": "Alafasy/mp3/053015.mp3",
        "segments": [
          [
            0,
            1,
            30,
            1930
          ],
          [
            1,
            2,
            1940,
            3660
          ],
          [
            2,
            3,
            3670,
            5050
          ]
        ]
      },
      "translations": [
        {
          "id": 662742,
          "resource_id": 101,
          "text": "Жаннати маъво ҳам ўша (Нилуфар)нинг олдидадир."
        }
      ],
      "audio_url": "https://audio.quran.com/reciters/7/Alafasy/mp3/053015.mp3"
    },
    {
      "id": 4800,
      "verse_number": 16,
      "verse_key": "53:16",
      "hizb_number": 53,
      "rub_el_hizb_number": 210,
      "ruku_number": 462,
      "manzil_number": 7,
      "sajdah_number": null,
      "text_uthmani": "إِذْ يَغْشَى ٱلسِّدْرَةَ مَا يَغْشَىٰ",
      "text_uthmani_tajweed": "إِذْ يَغْشَى <tajweed class=ham_wasl>ٱ</tajweed><tajweed class=laam_shamsiyah>ل</tajweed>سِّ<tajweed class=qalaqah>دْ</tajweed>رَةَ مَا يَغْشَىٰ <span class=end>١٦</span>",
      "page_number": 526,
      "juz_number": 27,
      "audio": {
        "url": "Alafasy/mp3/053016.mp3",
        "segments": [
          [
            0,
            1,
            30,
            380
          ],
          [
            1,
            2,
            390,
            1080
          ],
          [
            2,
            3,
            1090,
            2270
          ],
          [
            3,
            4,
            2280,
            2700
          ],
          [
            4,
            5,
            2710,
            4020
          ]
        ]
      },
      "translations": [
        {
          "id": 662743,
          "resource_id": 101,
          "text": "Ўшанда Нилуфарни ўраган нарса (яъни, Аллоҳ таолонинг файзи илоҳийси) ўраб олган эди."
        }
      ],
      "audio_url": "https://audio.quran.com/reciters/7/Alafasy/mp3/053016.mp3"
    },
    {
      "id": 4801,
      "verse_number": 17,
      "verse_key": "53:17",
      "hizb_number": 53,
      "rub_el_hizb_number": 210,
      "ruku_number": 462,
      "manzil_number": 7,
      "sajdah_number": null,
      "text_uthmani": "مَا زَاغَ ٱلْبَصَرُ وَمَا طَغَىٰ",
      "text_uthmani_tajweed": "مَا زَاغَ <tajweed class=ham_wasl>ٱ</tajweed>لْبَصَرُ وَمَا طَغَىٰ <span class=end>١٧</span>",
      "page_number": 526,
      "juz_number": 27,
      "audio": {
        "url": "Alafasy/mp3/053017.mp3",
        "segments": [
          [
            0,
            1,
            50,
            460
          ],
          [
            1,
            2,
            470,
            1230
          ],
          [
            2,
            3,
            1240,
            2190
          ],
          [
            3,
            4,
            2200,
            2820
          ],
          [
            4,
            5,
            2830,
            3870
          ]
        ]
      },
      "translations": [
        {
          "id": 662744,
          "resource_id": 101,
          "text": "(Пайғамбарнинг) кўзи (ўнгу сўлга) оғгани ҳам йўқ, ўз ҳаддидан ошгани ҳам йўқ."
        }
      ],
      "audio_url": "https://audio.quran.com/reciters/7/Alafasy/mp3/053017.mp3"
    },
    {
      "id": 4802,
      "verse_number": 18,
      "verse_key": "53:18",
      "hizb_number": 53,
      "rub_el_hizb_number": 210,
      "ruku_number": 462,
      "manzil_number": 7,
      "sajdah_number": null,
      "text_uthmani": "لَقَدْ رَأَىٰ مِنْ ءَايَـٰتِ رَبِّهِ ٱلْكُبْرَىٰٓ",
      "text_uthmani_tajweed": "لَقَ<tajweed class=qalaqah>دْ</tajweed> رَأَىٰ مِنْ ءَايَ<tajweed class=madda_normal>ـٰ</tajweed>تِ رَبِّهِ <tajweed class=ham_wasl>ٱ</tajweed>لْكُ<tajweed class=qalaqah>بْ</tajweed>رَىٰٓ <span class=end>١٨</span>",
      "page_number": 526,
      "juz_number": 27,
      "audio": {
        "url": "Alafasy/mp3/053018.mp3",
        "segments": [
          [
            0,
            1,
            30,
            610
          ],
          [
            1,
            2,
            620,
            1350
          ],
          [
            2,
            3,
            1360,
            1790
          ],
          [
            3,
            4,
            1800,
            2980
          ],
          [
            4,
            5,
            2990,
            3970
          ],
          [
            5,
            6,
            3980,
            5290
          ]
        ]
      },
      "translations": [
        {
          "id": 662745,
          "resource_id": 101,
          "text": "Дарҳақиқат, у (ўша соатда) Парвардигорининг буюк оятларини (яъни, У зотнинг қудрати илоҳийсига далолат қиладиган жуда кўп аломатларни) кўрди."
        }
      ],
      "audio_url": "https://audio.quran.com/reciters/7/Alafasy/mp3/053018.mp3"
    },
    {
      "id": 4803,
      "verse_number": 19,
      "verse_key": "53:19",
      "hizb_number": 53,
      "rub_el_hizb_number": 210,
      "ruku_number": 462,
      "manzil_number": 7,
      "sajdah_number": null,
      "text_uthmani": "أَفَرَءَيْتُمُ ٱللَّـٰتَ وَٱلْعُزَّىٰ",
      "text_uthmani_tajweed": "أَفَرَءَيْتُمُ <tajweed class=ham_wasl>ٱ</tajweed><tajweed class=laam_shamsiyah>ل</tajweed>لَّ<tajweed class=madda_normal>ـٰ</tajweed>تَ وَ<tajweed class=ham_wasl>ٱ</tajweed>لْعُزَّىٰ <span class=end>١٩</span>",
      "page_number": 526,
      "juz_number": 27,
      "audio": {
        "url": "Alafasy/mp3/053019.mp3",
        "segments": [
          [
            0,
            1,
            30,
            1610
          ],
          [
            1,
            2,
            1620,
            2620
          ],
          [
            2,
            3,
            2630,
            4520
          ]
        ]
      },
      "translations": [
        {
          "id": 662746,
          "resource_id": 101,
          "text": "(Эй мушриклар, ўзларингизча сиғинаётган санамларингиз) — «Лот», «Уззо» ҳақида ҳеч ўйлаб кўрдингларми?!"
        }
      ],
      "audio_url": "https://audio.quran.com/reciters/7/Alafasy/mp3/053019.mp3"
    },
    {
      "id": 4804,
      "verse_number": 20,
      "verse_key": "53:20",
      "hizb_number": 53,
      "rub_el_hizb_number": 210,
      "ruku_number": 462,
      "manzil_number": 7,
      "sajdah_number": null,
      "text_uthmani": "وَمَنَوٰةَ ٱلثَّالِثَةَ ٱلْأُخْرَىٰٓ",
      "text_uthmani_tajweed": "وَمَنَ<tajweed class=slnt>و</tajweed><tajweed class=madda_normal>ٲ</tajweed>ةَ <tajweed class=ham_wasl>ٱ</tajweed><tajweed class=laam_shamsiyah>ل</tajweed>ثَّالِثَةَ <tajweed class=ham_wasl>ٱ</tajweed>لْأُخْرَىٰٓ <span class=end>٢٠</span>",
      "page_number": 526,
      "juz_number": 27,
      "audio": {
        "url": "Alafasy/mp3/053020.mp3",
        "segments": [
          [
            0,
            1,
            30,
            1160
          ],
          [
            1,
            2,
            1170,
            2580
          ],
          [
            2,
            3,
            2590,
            4020
          ]
        ]
      },
      "translations": [
        {
          "id": 662747,
          "resource_id": 101,
          "text": "Ва яна учинчилари бўлмиш тубан «Манот» ҳақидачи?!"
        }
      ],
      "audio_url": "https://audio.quran.com/reciters/7/Alafasy/mp3/053020.mp3"
    },
    {
      "id": 4805,
      "verse_number": 21,
      "verse_key": "53:21",
      "hizb_number": 53,
      "rub_el_hizb_number": 210,
      "ruku_number": 462,
      "manzil_number": 7,
      "sajdah_number": null,
      "text_uthmani": "أَلَكُمُ ٱلذَّكَرُ وَلَهُ ٱلْأُنثَىٰ",
      "text_uthmani_tajweed": "أَلَكُمُ <tajweed class=ham_wasl>ٱ</tajweed><tajweed class=laam_shamsiyah>ل</tajweed>ذَّكَرُ وَلَهُ <tajweed class=ham_wasl>ٱ</tajweed>لْأُ<tajweed class=ikhafa>نث</tajweed>َىٰ <span class=end>٢١</span>",
      "page_number": 526,
      "juz_number": 27,
      "audio": {
        "url": "Alafasy/mp3/053021.mp3",
        "segments": [
          [
            0,
            1,
            30,
            870
          ],
          [
            1,
            2,
            880,
            1820
          ],
          [
            2,
            3,
            1830,
            2570
          ],
          [
            3,
            4,
            2580,
            4760
          ]
        ]
      },
      "translations": [
        {
          "id": 662748,
          "resource_id": 101,
          "text": "(Сизлар ўша бут-санамларни ва фаришталарни «Аллоҳнинг қизлари», дейсизлар, демак) эркак (жинси) сизларники-ю, аёл (жинси) У зотникими?!"
        }
      ],
      "audio_url": "https://audio.quran.com/reciters/7/Alafasy/mp3/053021.mp3"
    },
    {
      "id": 4806,
      "verse_number": 22,
      "verse_key": "53:22",
      "hizb_number": 53,
      "rub_el_hizb_number": 210,
      "ruku_number": 462,
      "manzil_number": 7,
      "sajdah_number": null,
      "text_uthmani": "تِلْكَ إِذًا قِسْمَةٌ ضِيزَىٰٓ",
      "text_uthmani_tajweed": "تِلْكَ إِ<tajweed class=ikhafa>ذًا ق</tajweed>ِسْمَ<tajweed class=ikhafa>ةٌ ض</tajweed>ِيزَىٰٓ <span class=end>٢٢</span>",
      "page_number": 526,
      "juz_number": 27,
      "audio": {
        "url": "Alafasy/mp3/053022.mp3",
        "segments": [
          [
            0,
            1,
            30,
            610
          ],
          [
            1,
            2,
            620,
            1080
          ],
          [
            2,
            3,
            1090,
            4390
          ],
          [
            3,
            4,
            4400,
            5770
          ]
        ]
      },
      "translations": [
        {
          "id": 662749,
          "resource_id": 101,
          "text": "У ҳолда бу адолатсиз тақсим-ку?!"
        }
      ],
      "audio_url": "https://audio.quran.com/reciters/7/Alafasy/mp3/053022.mp3"
    },
    {
      "id": 4807,
      "verse_number": 23,
      "verse_key": "53:23",
      "hizb_number": 53,
      "rub_el_hizb_number": 210,
      "ruku_number": 462,
      "manzil_number": 7,
      "sajdah_number": null,
      "text_uthmani": "إِنْ هِىَ إِلَّآ أَسْمَآءٌ سَمَّيْتُمُوهَآ أَنتُمْ وَءَابَآؤُكُم مَّآ أَنزَلَ ٱللَّهُ بِهَا مِن سُلْطَـٰنٍ ۚ إِن يَتَّبِعُونَ إِلَّا ٱلظَّنَّ وَمَا تَهْوَى ٱلْأَنفُسُ ۖ وَلَقَدْ جَآءَهُم مِّن رَّبِّهِمُ ٱلْهُدَىٰٓ",
      "text_uthmani_tajweed": "إِنْ هِىَ إِلّ<tajweed class=madda_obligatory>َآ</tajweed> أَسْم<tajweed class=madda_obligatory>َا</tajweed>ٓ<tajweed class=ikhafa>ءٌ س</tajweed>َ<tajweed class=ghunnah>مّ</tajweed>َيْتُمُوه<tajweed class=madda_obligatory>َآ</tajweed> أَ<tajweed class=ikhafa>نت</tajweed>ُمْ وَءَاب<tajweed class=madda_obligatory>َا</tajweed>ٓؤُك<tajweed class=idgham_shafawi>ُم م</tajweed>ّ<tajweed class=madda_obligatory>َآ</tajweed> أَ<tajweed class=ikhafa>نز</tajweed>َلَ <tajweed class=ham_wasl>ٱ</tajweed>للَّهُ بِهَا مِ<tajweed class=ikhafa>ن س</tajweed>ُلْطَ<tajweed class=madda_normal>ـٰ</tajweed>نٍ‌ۚ إ<tajweed class=idgham_ghunnah>ِن ي</tajweed>َتَّبِعُونَ إِلَّا <tajweed class=ham_wasl>ٱ</tajweed><tajweed class=laam_shamsiyah>ل</tajweed>ظَّ<tajweed class=ghunnah>نّ</tajweed>َ وَمَا تَهْوَى <tajweed class=ham_wasl>ٱ</tajweed>لْأَ<tajweed class=ikhafa>نف</tajweed>ُسُ‌ۖ وَلَقَ<tajweed class=qalaqah>دْ</tajweed> ج<tajweed class=madda_obligatory>َا</tajweed>ٓءَه<tajweed class=idgham_shafawi>ُم م</tajweed>ّ<tajweed class=idgham_wo_ghunnah>ِن ر</tajweed>َّبِّهِمُ <tajweed class=ham_wasl>ٱ</tajweed>لْهُدَىٰٓ <span class=end>٢٣</span>",
      "page_number": 526,
      "juz_number": 27,
      "audio": {
        "url": "Alafasy/mp3/053023.mp3",
        "segments": [
          [
            0,
            1,
            30,
            430
          ],
          [
            1,
            2,
            440,
            880
          ],
          [
            2,
            3,
            890,
            2880
          ],
          [
            3,
            4,
            2890,
            6430
          ],
          [
            4,
            5,
            6440,
            13030
          ],
          [
            5,
            6,
            13040,
            15830
          ],
          [
            6,
            7,
            15840,
            19860
          ],
          [
            7,
            8,
            19870,
            19880
          ],
          [
            8,
            9,
            19890,
            22880
          ],
          [
            9,
            10,
            22890,
            23810
          ],
          [
            10,
            11,
            23820,
            24530
          ],
          [
            11,
            12,
            24540,
            25710
          ],
          [
            12,
            13,
            25720,
            29390
          ],
          [
            13,
            14,
            29400,
            30340
          ],
          [
            14,
            15,
            30350,
            31890
          ],
          [
            15,
            16,
            31900,
            32530
          ],
          [
            16,
            17,
            32540,
            34110
          ],
          [
            17,
            18,
            34120,
            34760
          ],
          [
            18,
            19,
            34770,
            35510
          ],
          [
            19,
            20,
            35520,
            38310
          ],
          [
            20,
            21,
            38320,
            39130
          ],
          [
            21,
            22,
            39140,
            42960
          ],
          [
            22,
            23,
            42970,
            43100
          ],
          [
            23,
            24,
            43110,
            44530
          ],
          [
            24,
            25,
            44540,
            45670
          ]
        ]
      },
      "translations": [
        {
          "id": 662750,
          "resource_id": 101,
          "text": "У (ном)лар фақат сизлар ўзларингиз ва ота-боболарингиз қўйиб олган номлардир. Аллоҳ улар(га ибодат қилиш) ҳақида бирон ҳужжат туширган эмас. У (мушрик)ларга (Пайғамбар алайҳис-салоту вас-салом воситаларида) Парвардигор томонидан ҳидоят (Қуръон) келиб турган ҳолда улар фақат гумонга ва ҳавойи нафсларигагина эргашадилар-а!"
        }
      ],
      "audio_url": "https://audio.quran.com/reciters/7/Alafasy/mp3/053023.mp3"
    },
    {
      "id": 4808,
      "verse_number": 24,
      "verse_key": "53:24",
      "hizb_number": 53,
      "rub_el_hizb_number": 210,
      "ruku_number": 462,
      "manzil_number": 7,
      "sajdah_number": null,
      "text_uthmani": "أَمْ لِلْإِنسَـٰنِ مَا تَمَنَّىٰ",
      "text_uthmani_tajweed": "أَمْ لِلْإِ<tajweed class=ikhafa>نس</tajweed>َ<tajweed class=madda_normal>ـٰ</tajweed>نِ مَا تَمَ<tajweed class=ghunnah>نّ</tajweed>َىٰ <span class=end>٢٤</span>",
      "page_number": 526,
      "juz_number": 27,
      "audio": {
        "url": "Alafasy/mp3/053024.mp3",
        "segments": [
          [
            0,
            1,
            40,
            390
          ],
          [
            1,
            2,
            400,
            2830
          ],
          [
            2,
            3,
            2840,
            3200
          ],
          [
            3,
            4,
            3210,
            5670
          ]
        ]
      },
      "translations": [
        {
          "id": 662751,
          "resource_id": 101,
          "text": "Ёки инсон учун ўзи орзу қилган нарса бўлаверарми?! (Ҳаргиз бўлмас!) <sup foot_note=145271>1</sup>"
        }
      ],
      "audio_url": "https://audio.quran.com/reciters/7/Alafasy/mp3/053024.mp3"
    },
    {
      "id": 4809,
      "verse_number": 25,
      "verse_key": "53:25",
      "hizb_number": 53,
      "rub_el_hizb_number": 210,
      "ruku_number": 462,
      "manzil_number": 7,
      "sajdah_number": null,
      "text_uthmani": "فَلِلَّهِ ٱلْـَٔاخِرَةُ وَٱلْأُولَىٰ",
      "text_uthmani_tajweed": "فَلِلَّهِ <tajweed class=ham_wasl>ٱ</tajweed>لْأَخِرَةُ وَ<tajweed class=ham_wasl>ٱ</tajweed>لْأُولَىٰ <span class=end>٢٥</span>",
      "page_number": 526,
      "juz_number": 27,
      "audio": {
        "url": "Alafasy/mp3/053025.mp3",
        "segments": [
          [
            0,
            1,
            30,
            1290
          ],
          [
            1,
            2,
            1300,
            2650
          ],
          [
            2,
            3,
            2660,
            4270
          ]
        ]
      },
      "translations": [
        {
          "id": 662752,
          "resource_id": 101,
          "text": "Зеро, Охират ҳам, дунё ҳам ёлғиз Аллоҳникидир!"
        }
      ],
      "audio_url": "https://audio.quran.com/reciters/7/Alafasy/mp3/053025.mp3"
    },
    {
      "id": 4810,
      "verse_number": 26,
      "verse_key": "53:26",
      "hizb_number": 53,
      "rub_el_hizb_number": 211,
      "ruku_number": 463,
      "manzil_number": 7,
      "sajdah_number": null,
      "text_uthmani": "۞ وَكَم مِّن مَّلَكٍ فِى ٱلسَّمَـٰوَٰتِ لَا تُغْنِى شَفَـٰعَتُهُمْ شَيْـًٔا إِلَّا مِنۢ بَعْدِ أَن يَأْذَنَ ٱللَّهُ لِمَن يَشَآءُ وَيَرْضَىٰٓ",
      "text_uthmani_tajweed": "۞ وَك<tajweed class=idgham_shafawi>َم م</tajweed>ّ<tajweed class=idgham_ghunnah>ِن م</tajweed>َّلَ<tajweed class=ikhafa>كٍ ف</tajweed>ِى <tajweed class=ham_wasl>ٱ</tajweed><tajweed class=laam_shamsiyah>ل</tajweed>سَّمَ<tajweed class=madda_normal>ـٰ</tajweed>و<tajweed class=madda_normal>َٲ</tajweed>تِ لَا تُغْنِى شَفَ<tajweed class=madda_normal>ـٰ</tajweed>عَتُهُمْ شَيْــًٔا إِلَّا م<tajweed class=iqlab>ِنۢ ب</tajweed>َعْدِ أ<tajweed class=idgham_ghunnah>َن ي</tajweed>َأْذَنَ <tajweed class=ham_wasl>ٱ</tajweed>للَّهُ لِم<tajweed class=idgham_ghunnah>َن ي</tajweed>َش<tajweed class=madda_obligatory>َا</tajweed>ٓءُ وَيَرْضَىٰٓ <span class=end>٢٦</span>",
      "page_number": 526,
      "juz_number": 27,
      "audio": {
        "url": "Alafasy/mp3/053026.mp3",
        "segments": [
          [
            0,
            1,
            30,
            1360
          ],
          [
            1,
            2,
            1370,
            2520
          ],
          [
            2,
            3,
            2530,
            3950
          ],
          [
            3,
            4,
            3960,
            4220
          ],
          [
            4,
            5,
            4230,
            5900
          ],
          [
            5,
            6,
            5910,
            6270
          ],
          [
            6,
            7,
            6280,
            7140
          ],
          [
            7,
            8,
            7150,
            8790
          ],
          [
            8,
            9,
            8800,
            14290
          ],
          [
            9,
            10,
            14300,
            15270
          ],
          [
            10,
            11,
            15280,
            16540
          ],
          [
            11,
            12,
            16550,
            17260
          ],
          [
            12,
            13,
            17270,
            18210
          ],
          [
            13,
            14,
            18220,
            19040
          ],
          [
            14,
            15,
            19050,
            20030
          ],
          [
            15,
            16,
            20040,
            21130
          ],
          [
            16,
            17,
            21140,
            23430
          ],
          [
            17,
            18,
            23440,
            24700
          ]
        ]
      },
      "translations": [
        {
          "id": 662753,
          "resource_id": 101,
          "text": "Осмонларда қанчадан-қанча фаришталар бўлиб, ўшаларнинг шафоатлари ҳам бирон фойда бермас, магар Аллоҳ Ўзи хоҳлаган рози бўлган кишилар учун (шафоатга) изн берганидан кейингина (у шафоатнинг фойдаси тегур)."
        }
      ],
      "audio_url": "https://audio.quran.com/reciters/7/Alafasy/mp3/053026.mp3"
    },
    {
      "id": 4811,
      "verse_number": 27,
      "verse_key": "53:27",
      "hizb_number": 53,
      "rub_el_hizb_number": 211,
      "ruku_number": 463,
      "manzil_number": 7,
      "sajdah_number": null,
      "text_uthmani": "إِنَّ ٱلَّذِينَ لَا يُؤْمِنُونَ بِٱلْـَٔاخِرَةِ لَيُسَمُّونَ ٱلْمَلَـٰٓئِكَةَ تَسْمِيَةَ ٱلْأُنثَىٰ",
      "text_uthmani_tajweed": "إِ<tajweed class=ghunnah>نّ</tajweed>َ <tajweed class=ham_wasl>ٱ</tajweed>لَّذِينَ لَا يُؤْمِنُونَ بِ<tajweed class=ham_wasl>ٱ</tajweed>لْأَخِرَةِ لَيُسَ<tajweed class=ghunnah>مّ</tajweed>ُونَ <tajweed class=ham_wasl>ٱ</tajweed>لْمَلَ<tajweed class=madda_obligatory>ـٰٓ</tajweed>ئِكَةَ تَسْمِيَةَ <tajweed class=ham_wasl>ٱ</tajweed>لْأُ<tajweed class=ikhafa>نث</tajweed>َىٰ <span class=end>٢٧</span>",
      "page_number": 527,
      "juz_number": 27,
      "audio": {
        "url": "Alafasy/mp3/053027.mp3",
        "segments": [
          [
            0,
            1,
            30,
            1710
          ],
          [
            1,
            2,
            1720,
            2920
          ],
          [
            2,
            3,
            2930,
            3340
          ],
          [
            3,
            4,
            3350,
            4750
          ],
          [
            4,
            5,
            4760,
            6370
          ],
          [
            5,
            6,
            6380,
            8710
          ],
          [
            6,
            7,
            8720,
            11800
          ],
          [
            7,
            8,
            11810,
            12930
          ],
          [
            8,
            9,
            12940,
            15100
          ]
        ]
      },
      "translations": [
        {
          "id": 662754,
          "resource_id": 101,
          "text": "Дарвоқеъ, Охиратга иймон келтирмайдиган кимсалар фаришталарни аёллар номи билан атайдилар."
        }
      ],
      "audio_url": "https://audio.quran.com/reciters/7/Alafasy/mp3/053027.mp3"
    },
    {
      "id": 4812,
      "verse_number": 28,
      "verse_key": "53:28",
      "hizb_number": 53,
      "rub_el_hizb_number": 211,
      "ruku_number": 463,
      "manzil_number": 7,
      "sajdah_number": null,
      "text_uthmani": "وَمَا لَهُم بِهِۦ مِنْ عِلْمٍ ۖ إِن يَتَّبِعُونَ إِلَّا ٱلظَّنَّ ۖ وَإِنَّ ٱلظَّنَّ لَا يُغْنِى مِنَ ٱلْحَقِّ شَيْـًٔا",
      "text_uthmani_tajweed": "وَمَا لَه<tajweed class=ikhafa_shafawi>ُم ب</tajweed>ِه<tajweed class=madda_normal>ِۦ</tajweed> مِنْ عِلْمٍ‌ۖ إ<tajweed class=idgham_ghunnah>ِن ي</tajweed>َتَّبِعُونَ إِلَّا <tajweed class=ham_wasl>ٱ</tajweed><tajweed class=laam_shamsiyah>ل</tajweed>ظَّ<tajweed class=ghunnah>نّ</tajweed>َ‌ۖ وَإِ<tajweed class=ghunnah>نّ</tajweed>َ <tajweed class=ham_wasl>ٱ</tajweed><tajweed class=laam_shamsiyah>ل</tajweed>ظَّ<tajweed class=ghunnah>نّ</tajweed>َ لَا يُغْنِى مِنَ <tajweed class=ham_wasl>ٱ</tajweed>لْحَقِّ شَيْــًٔا <span class=end>٢٨</span>",
      "page_number": 527,
      "juz_number": 27,
      "audio": {
        "url": "Alafasy/mp3/053028.mp3",
        "segments": [
          [
            0,
            1,
            30,
            650
          ],
          [
            1,
            2,
            660,
            2160
          ],
          [
            2,
            3,
            2170,
            2900
          ],
          [
            3,
            4,
            2910,
            3300
          ],
          [
            4,
            5,
            3310,
            4470
          ],
          [
            5,
            6,
            4480,
            5880
          ],
          [
            6,
            7,
            5890,
            7210
          ],
          [
            7,
            8,
            7220,
            7840
          ],
          [
            8,
            9,
            7850,
            9570
          ],
          [
            9,
            10,
            9580,
            10980
          ],
          [
            10,
            11,
            10990,
            12350
          ],
          [
            11,
            12,
            12360,
            12740
          ],
          [
            12,
            13,
            12750,
            13700
          ],
          [
            13,
            14,
            13710,
            14120
          ],
          [
            14,
            15,
            14130,
            15040
          ],
          [
            15,
            16,
            15050,
            16140
          ]
        ]
      },
      "translations": [
        {
          "id": 662755,
          "resource_id": 101,
          "text": "Ҳолбуки, улар учун бу ҳақда (яъни, фаришталарнинг қайси жинсдан эканлиги ҳақида) бирон билим-ҳужжат йўқдир. Улар фақат гумон-тахминга эргашурлар, холос. Аниқки, гумон ҳақиқатдан бирон нарсанинг ўрнига ўтмас!"
        }
      ],
      "audio_url": "https://audio.quran.com/reciters/7/Alafasy/mp3/053028.mp3"
    },
    {
      "id": 4813,
      "verse_number": 29,
      "verse_key": "53:29",
      "hizb_number": 53,
      "rub_el_hizb_number": 211,
      "ruku_number": 463,
      "manzil_number": 7,
      "sajdah_number": null,
      "text_uthmani": "فَأَعْرِضْ عَن مَّن تَوَلَّىٰ عَن ذِكْرِنَا وَلَمْ يُرِدْ إِلَّا ٱلْحَيَوٰةَ ٱلدُّنْيَا",
      "text_uthmani_tajweed": "فَأَعْرِضْ ع<tajweed class=idgham_ghunnah>َن م</tajweed>َّ<tajweed class=ikhafa>ن ت</tajweed>َوَلَّىٰ عَ<tajweed class=ikhafa>ن ذ</tajweed>ِكْرِنَا وَلَمْ يُرِ<tajweed class=qalaqah>دْ</tajweed> إِلَّا <tajweed class=ham_wasl>ٱ</tajweed>لْحَيَ<tajweed class=slnt>و</tajweed><tajweed class=madda_normal>ٲ</tajweed>ةَ <tajweed class=ham_wasl>ٱ</tajweed><tajweed class=laam_shamsiyah>ل</tajweed>دُّنْيَا <span class=end>٢٩</span>",
      "page_number": 527,
      "juz_number": 27,
      "audio": {
        "url": "Alafasy/mp3/053029.mp3",
        "segments": [
          [
            0,
            1,
            30,
            1000
          ],
          [
            1,
            2,
            1010,
            2050
          ],
          [
            2,
            3,
            2060,
            2820
          ],
          [
            3,
            4,
            2830,
            3920
          ],
          [
            4,
            5,
            3930,
            5030
          ],
          [
            5,
            6,
            5040,
            6170
          ],
          [
            6,
            7,
            6180,
            6820
          ],
          [
            7,
            8,
            6830,
            7490
          ],
          [
            8,
            9,
            7500,
            8130
          ],
          [
            9,
            10,
            8140,
            9310
          ],
          [
            10,
            11,
            9320,
            10440
          ]
        ]
      },
      "translations": [
        {
          "id": 662756,
          "resource_id": 101,
          "text": "Бас, (эй Муҳаммад алайҳис-салоту вас-салом), сиз Бизнинг эслатмамиздан орқа ўгириб кетган ва фақат ҳаёти дунёнигина истаган кимсалардан юз ўгиринг!"
        }
      ],
      "audio_url": "https://audio.quran.com/reciters/7/Alafasy/mp3/053029.mp3"
    },
    {
      "id": 4814,
      "verse_number": 30,
      "verse_key": "53:30",
      "hizb_number": 53,
      "rub_el_hizb_number": 211,
      "ruku_number": 463,
      "manzil_number": 7,
      "sajdah_number": null,
      "text_uthmani": "ذَٰلِكَ مَبْلَغُهُم مِّنَ ٱلْعِلْمِ ۚ إِنَّ رَبَّكَ هُوَ أَعْلَمُ بِمَن ضَلَّ عَن سَبِيلِهِۦ وَهُوَ أَعْلَمُ بِمَنِ ٱهْتَدَىٰ",
      "text_uthmani_tajweed": "ذ<tajweed class=madda_normal>َٲ</tajweed>لِكَ مَ<tajweed class=qalaqah>بْ</tajweed>لَغُه<tajweed class=idgham_shafawi>ُم م</tajweed>ِّنَ <tajweed class=ham_wasl>ٱ</tajweed>لْعِلْمِ‌ۚ إِ<tajweed class=ghunnah>نّ</tajweed>َ رَبَّكَ هُوَ أَعْلَمُ بِمَ<tajweed class=ikhafa>ن ض</tajweed>َلَّ عَ<tajweed class=ikhafa>ن س</tajweed>َبِيلِه<tajweed class=madda_normal>ِۦ</tajweed> وَهُوَ أَعْلَمُ بِمَنِ <tajweed class=ham_wasl>ٱ</tajweed>هْتَدَىٰ <span class=end>٣٠</span>",
      "page_number": 527,
      "juz_number": 27,
      "audio": {
        "url": "Alafasy/mp3/053030.mp3",
        "segments": [
          [
            0,
            1,
            30,
            880
          ],
          [
            1,
            2,
            890,
            3060
          ],
          [
            2,
            3,
            3070,
            3370
          ],
          [
            3,
            4,
            3380,
            4650
          ],
          [
            4,
            5,
            4660,
            5690
          ],
          [
            5,
            6,
            5700,
            6550
          ],
          [
            6,
            7,
            6560,
            7000
          ],
          [
            7,
            8,
            7010,
            7920
          ],
          [
            8,
            9,
            7930,
            9220
          ],
          [
            9,
            10,
            9230,
            9830
          ],
          [
            10,
            11,
            9840,
            10740
          ],
          [
            11,
            12,
            10750,
            12170
          ],
          [
            12,
            13,
            12180,
            12880
          ],
          [
            13,
            14,
            12890,
            13750
          ],
          [
            14,
            15,
            13760,
            14370
          ],
          [
            15,
            16,
            14380,
            15650
          ]
        ]
      },
      "translations": [
        {
          "id": 662757,
          "resource_id": 101,
          "text": "Уларнинг «илм»дан етган жойлари мана шу (ҳаёти дунё матоларинигина исташ)дир. Албатта Парвардигорингизнинг Ўзи Унинг йўлидан озган кимсаларни жуда яхши билгувчидир ва У ҳидоят топган зотларни ҳам жуда яхши билгувчидир."
        }
      ],
      "audio_url": "https://audio.quran.com/reciters/7/Alafasy/mp3/053030.mp3"
    },
    {
      "id": 4815,
      "verse_number": 31,
      "verse_key": "53:31",
      "hizb_number": 53,
      "rub_el_hizb_number": 211,
      "ruku_number": 463,
      "manzil_number": 7,
      "sajdah_number": null,
      "text_uthmani": "وَلِلَّهِ مَا فِى ٱلسَّمَـٰوَٰتِ وَمَا فِى ٱلْأَرْضِ لِيَجْزِىَ ٱلَّذِينَ أَسَـٰٓـُٔوا۟ بِمَا عَمِلُوا۟ وَيَجْزِىَ ٱلَّذِينَ أَحْسَنُوا۟ بِٱلْحُسْنَى",
      "text_uthmani_tajweed": "وَلِلَّهِ مَا فِى <tajweed class=ham_wasl>ٱ</tajweed><tajweed class=laam_shamsiyah>ل</tajweed>سَّمَ<tajweed class=madda_normal>ـٰ</tajweed>و<tajweed class=madda_normal>َٲ</tajweed>تِ وَمَا فِى <tajweed class=ham_wasl>ٱ</tajweed>لْأَرْضِ لِيَ<tajweed class=qalaqah>جْ</tajweed>زِىَ <tajweed class=ham_wasl>ٱ</tajweed>لَّذِينَ أَسَ<tajweed class=madda_obligatory>ـٰٓـ</tajweed>ــُٔو<tajweed class=slnt>اْ</tajweed> بِمَا عَمِلُو<tajweed class=slnt>اْ</tajweed> وَيَ<tajweed class=qalaqah>جْ</tajweed>زِىَ <tajweed class=ham_wasl>ٱ</tajweed>لَّذِينَ أَحْسَنُو<tajweed class=slnt>اْ</tajweed> بِ<tajweed class=ham_wasl>ٱ</tajweed>لْحُسْنَى <span class=end>٣١</span>",
      "page_number": 527,
      "juz_number": 27,
      "audio": {
        "url": "Alafasy/mp3/053031.mp3",
        "segments": [
          [
            0,
            1,
            30,
            1420
          ],
          [
            1,
            2,
            1430,
            1770
          ],
          [
            2,
            3,
            1780,
            2020
          ],
          [
            3,
            4,
            2030,
            3670
          ],
          [
            4,
            5,
            3680,
            4320
          ],
          [
            5,
            6,
            4330,
            4630
          ],
          [
            6,
            7,
            4640,
            5580
          ],
          [
            7,
            8,
            5590,
            6690
          ],
          [
            8,
            9,
            6700,
            7820
          ],
          [
            9,
            10,
            7830,
            10810
          ],
          [
            10,
            11,
            10820,
            11480
          ],
          [
            11,
            12,
            11490,
            12500
          ],
          [
            12,
            13,
            12510,
            13570
          ],
          [
            13,
            14,
            13580,
            14760
          ],
          [
            14,
            15,
            14770,
            15850
          ],
          [
            15,
            16,
            15860,
            17390
          ]
        ]
      },
      "translations": [
        {
          "id": 662758,
          "resource_id": 101,
          "text": "Осмонлардаги ва Ердаги бор нарсалар ёлғиз Аллоҳникидир. У зотнинг Ўзи ёмонлик-гуноҳ қилиб ўтган кимсаларни қилган амаллари билан жазолагай ва чиройли амал қилган зотларни гўзал (савоб-жаннат) билан мукофотлагай!"
        }
      ],
      "audio_url": "https://audio.quran.com/reciters/7/Alafasy/mp3/053031.mp3"
    },
    {
      "id": 4816,
      "verse_number": 32,
      "verse_key": "53:32",
      "hizb_number": 53,
      "rub_el_hizb_number": 211,
      "ruku_number": 463,
      "manzil_number": 7,
      "sajdah_number": null,
      "text_uthmani": "ٱلَّذِينَ يَجْتَنِبُونَ كَبَـٰٓئِرَ ٱلْإِثْمِ وَٱلْفَوَٰحِشَ إِلَّا ٱللَّمَمَ ۚ إِنَّ رَبَّكَ وَٰسِعُ ٱلْمَغْفِرَةِ ۚ هُوَ أَعْلَمُ بِكُمْ إِذْ أَنشَأَكُم مِّنَ ٱلْأَرْضِ وَإِذْ أَنتُمْ أَجِنَّةٌ فِى بُطُونِ أُمَّهَـٰتِكُمْ ۖ فَلَا تُزَكُّوٓا۟ أَنفُسَكُمْ ۖ هُوَ أَعْلَمُ بِمَنِ ٱتَّقَىٰٓ",
      "text_uthmani_tajweed": "ٱلَّذِينَ يَ<tajweed class=qalaqah>جْ</tajweed>تَنِبُونَ كَبَ<tajweed class=madda_obligatory>ـٰٓ</tajweed>ئِرَ <tajweed class=ham_wasl>ٱ</tajweed>لْإِثْمِ وَ<tajweed class=ham_wasl>ٱ</tajweed>لْفَو<tajweed class=madda_normal>َٲ</tajweed>حِشَ إِلَّا <tajweed class=ham_wasl>ٱ</tajweed><tajweed class=laam_shamsiyah>ل</tajweed>لَّمَمَ‌ۚ إِ<tajweed class=ghunnah>نّ</tajweed>َ رَبَّكَ و<tajweed class=madda_normal>َٲ</tajweed>سِعُ <tajweed class=ham_wasl>ٱ</tajweed>لْمَغْفِرَةِ‌ۚ هُوَ أَعْلَمُ بِكُمْ إِذْ أَ<tajweed class=ikhafa>نش</tajweed>َأَك<tajweed class=idgham_shafawi>ُم م</tajweed>ِّنَ <tajweed class=ham_wasl>ٱ</tajweed>لْأَرْضِ وَإِذْ أَ<tajweed class=ikhafa>نت</tajweed>ُمْ أَجِ<tajweed class=ghunnah>نّ</tajweed>َ<tajweed class=ikhafa>ةٌ ف</tajweed>ِى بُطُونِ أُ<tajweed class=ghunnah>مّ</tajweed>َهَ<tajweed class=madda_normal>ـٰ</tajweed>تِكُمْ‌ۖ فَلَا تُزَكّ<tajweed class=madda_obligatory>ُوٓ</tajweed><tajweed class=slnt>اْ</tajweed> أَ<tajweed class=ikhafa>نف</tajweed>ُسَكُمْ‌ۖ هُوَ أَعْلَمُ بِمَنِ <tajweed class=ham_wasl>ٱ</tajweed>تَّقَىٰٓ <span class=end>٣٢</span>",
      "page_number": 527,
      "juz_number": 27,
      "audio": {
        "url": "Alafasy/mp3/053032.mp3",
        "segments": [
          [
            0,
            1,
            30,
            1280
          ],
          [
            1,
            2,
            1290,
            2840
          ],
          [
            2,
            3,
            2850,
            5500
          ],
          [
            3,
            4,
            5510,
            6400
          ],
          [
            4,
            5,
            6410,
            8030
          ],
          [
            5,
            6,
            8040,
            8710
          ],
          [
            6,
            7,
            8720,
            10180
          ],
          [
            7,
            8,
            10190,
            11410
          ],
          [
            8,
            9,
            11420,
            12350
          ],
          [
            9,
            10,
            12360,
            13220
          ],
          [
            10,
            11,
            13230,
            15100
          ],
          [
            11,
            12,
            15110,
            15510
          ],
          [
            12,
            13,
            15520,
            16370
          ],
          [
            13,
            14,
            16380,
            17060
          ],
          [
            14,
            15,
            17070,
            17490
          ],
          [
            15,
            16,
            17500,
            20020
          ],
          [
            16,
            17,
            20030,
            20320
          ],
          [
            17,
            18,
            20330,
            21310
          ],
          [
            18,
            19,
            21320,
            21970
          ],
          [
            19,
            20,
            21980,
            23500
          ],
          [
            20,
            21,
            23510,
            25970
          ],
          [
            21,
            22,
            25980,
            26470
          ],
          [
            22,
            23,
            26480,
            27420
          ],
          [
            23,
            24,
            27430,
            30510
          ],
          [
            24,
            25,
            30520,
            31160
          ],
          [
            25,
            26,
            31170,
            34180
          ],
          [
            26,
            27,
            34190,
            36690
          ],
          [
            27,
            28,
            36700,
            37090
          ],
          [
            28,
            29,
            37100,
            37970
          ],
          [
            29,
            30,
            37980,
            38630
          ],
          [
            30,
            31,
            38640,
            39910
          ]
        ]
      },
      "translations": [
        {
          "id": 662759,
          "resource_id": 101,
          "text": "Улар (яъни, жаннатга сазовор бўлганлар) кичик хатолардан бошқа катта гуноҳлардан ва бузуқликлардан йироқ бўладиган зотлардир. Албатта Парвардигорингиз мағфирати кенг Зотдир. У сизларни (яъни, оталарингиз Одамни) Ердан — тупроқдан пайдо қилган пайтиданоқ ва сизлар оналарингизнинг қорнида ҳомила бўлган пайтингизданоқ жуда яхши билгувчидир. Бас, сизлар ўзларингизни покламай қўя қолинглар! У тақводор бўлган кишиларни жуда яхши билгувчидир."
        }
      ],
      "audio_url": "https://audio.quran.com/reciters/7/Alafasy/mp3/053032.mp3"
    },
    {
      "id": 4817,
      "verse_number": 33,
      "verse_key": "53:33",
      "hizb_number": 53,
      "rub_el_hizb_number": 211,
      "ruku_number": 464,
      "manzil_number": 7,
      "sajdah_number": null,
      "text_uthmani": "أَفَرَءَيْتَ ٱلَّذِى تَوَلَّىٰ",
      "text_uthmani_tajweed": "أَفَرَءَيْتَ <tajweed class=ham_wasl>ٱ</tajweed>لَّذِى تَوَلَّىٰ <span class=end>٣٣</span>",
      "page_number": 527,
      "juz_number": 27,
      "audio": {
        "url": "Alafasy/mp3/053033.mp3",
        "segments": [
          [
            0,
            1,
            30,
            1250
          ],
          [
            1,
            2,
            1260,
            2160
          ],
          [
            2,
            3,
            2170,
            3740
          ]
        ]
      },
      "translations": [
        {
          "id": 662760,
          "resource_id": 101,
          "text": "(Эй Муҳаммад алайҳис-салоту вас-салом, иймондан) юз ўгириб кетган"
        }
      ],
      "audio_url": "https://audio.quran.com/reciters/7/Alafasy/mp3/053033.mp3"
    },
    {
      "id": 4818,
      "verse_number": 34,
      "verse_key": "53:34",
      "hizb_number": 53,
      "rub_el_hizb_number": 211,
      "ruku_number": 464,
      "manzil_number": 7,
      "sajdah_number": null,
      "text_uthmani": "وَأَعْطَىٰ قَلِيلًا وَأَكْدَىٰٓ",
      "text_uthmani_tajweed": "وَأَعْطَىٰ قَلِيل<tajweed class=idgham_ghunnah>اً و</tajweed>َأَكْدَىٰٓ <span class=end>٣٤</span>",
      "page_number": 527,
      "juz_number": 27,
      "audio": {
        "url": "Alafasy/mp3/053034.mp3",
        "segments": [
          [
            0,
            1,
            30,
            1050
          ],
          [
            1,
            2,
            1060,
            1960
          ],
          [
            2,
            3,
            1970,
            4260
          ]
        ]
      },
      "translations": [
        {
          "id": 662761,
          "resource_id": 101,
          "text": "ва озгина (мол) бериб, (кейин шарт қилинган молни беришни) тўхтатган кимсани кўрдингизми? <sup foot_note=145272>1</sup>"
        }
      ],
      "audio_url": "https://audio.quran.com/reciters/7/Alafasy/mp3/053034.mp3"
    },
    {
      "id": 4819,
      "verse_number": 35,
      "verse_key": "53:35",
      "hizb_number": 53,
      "rub_el_hizb_number": 211,
      "ruku_number": 464,
      "manzil_number": 7,
      "sajdah_number": null,
      "text_uthmani": "أَعِندَهُۥ عِلْمُ ٱلْغَيْبِ فَهُوَ يَرَىٰٓ",
      "text_uthmani_tajweed": "أَعِ<tajweed class=ikhafa>ند</tajweed>َهُ<tajweed class=madda_normal>ۥ</tajweed> عِلْمُ <tajweed class=ham_wasl>ٱ</tajweed>لْغَيْبِ فَهُوَ يَرَىٰٓ <span class=end>٣٥</span>",
      "page_number": 527,
      "juz_number": 27,
      "audio": {
        "url": "Alafasy/mp3/053035.mp3",
        "segments": [
          [
            0,
            1,
            30,
            1790
          ],
          [
            1,
            2,
            1800,
            2510
          ],
          [
            2,
            3,
            2520,
            3380
          ],
          [
            3,
            4,
            3390,
            4060
          ],
          [
            4,
            5,
            4070,
            4870
          ]
        ]
      },
      "translations": [
        {
          "id": 662762,
          "resource_id": 101,
          "text": "Унинг ҳузурида ғайб илми бормидики, у (келажакда бошқа биров ўзининг гуноҳини зиммасига олишини) билиб олса?!"
        }
      ],
      "audio_url": "https://audio.quran.com/reciters/7/Alafasy/mp3/053035.mp3"
    },
    {
      "id": 4820,
      "verse_number": 36,
      "verse_key": "53:36",
      "hizb_number": 53,
      "rub_el_hizb_number": 211,
      "ruku_number": 464,
      "manzil_number": 7,
      "sajdah_number": null,
      "text_uthmani": "أَمْ لَمْ يُنَبَّأْ بِمَا فِى صُحُفِ مُوسَىٰ",
      "text_uthmani_tajweed": "أَمْ لَمْ يُنَبَّأْ بِمَا فِى صُحُفِ مُوسَىٰ <span class=end>٣٦</span>",
      "page_number": 527,
      "juz_number": 27,
      "audio": {
        "url": "Alafasy/mp3/053036.mp3",
        "segments": [
          [
            0,
            1,
            30,
            370
          ],
          [
            1,
            2,
            380,
            780
          ],
          [
            2,
            3,
            790,
            1780
          ],
          [
            3,
            4,
            1790,
            2460
          ],
          [
            4,
            5,
            2470,
            2900
          ],
          [
            5,
            6,
            2910,
            3660
          ],
          [
            6,
            7,
            3670,
            5000
          ]
        ]
      },
      "translations": [
        {
          "id": 662763,
          "resource_id": 101,
          "text": "Ёки унга Мусонинг саҳифаларидаги сўзлар хабари берилмаганмиди?!"
        }
      ],
      "audio_url": "https://audio.quran.com/reciters/7/Alafasy/mp3/053036.mp3"
    },
    {
      "id": 4821,
      "verse_number": 37,
      "verse_key": "53:37",
      "hizb_number": 53,
      "rub_el_hizb_number": 211,
      "ruku_number": 464,
      "manzil_number": 7,
      "sajdah_number": null,
      "text_uthmani": "وَإِبْرَٰهِيمَ ٱلَّذِى وَفَّىٰٓ",
      "text_uthmani_tajweed": "وَإِ<tajweed class=qalaqah>بْ</tajweed>ر<tajweed class=madda_normal>َٲ</tajweed>هِيمَ <tajweed class=ham_wasl>ٱ</tajweed>لَّذِى وَفَّىٰٓ <span class=end>٣٧</span>",
      "page_number": 527,
      "juz_number": 27,
      "audio": {
        "url": "Alafasy/mp3/053037.mp3",
        "segments": [
          [
            0,
            1,
            30,
            1680
          ],
          [
            1,
            2,
            1690,
            2580
          ],
          [
            2,
            3,
            2590,
            3820
          ]
        ]
      },
      "translations": [
        {
          "id": 662764,
          "resource_id": 101,
          "text": "Ва (аҳдига) вафодор зот бўлган Иброҳимнинг саҳифаларидаги сўзлар (хабари берилмаганмиди?!)"
        }
      ],
      "audio_url": "https://audio.quran.com/reciters/7/Alafasy/mp3/053037.mp3"
    },
    {
      "id": 4822,
      "verse_number": 38,
      "verse_key": "53:38",
      "hizb_number": 53,
      "rub_el_hizb_number": 211,
      "ruku_number": 464,
      "manzil_number": 7,
      "sajdah_number": null,
      "text_uthmani": "أَلَّا تَزِرُ وَازِرَةٌ وِزْرَ أُخْرَىٰ",
      "text_uthmani_tajweed": "أَلَّا تَزِرُ وَازِرَ<tajweed class=idgham_ghunnah>ةٌ و</tajweed>ِزْرَ أُخْرَىٰ <span class=end>٣٨</span>",
      "page_number": 527,
      "juz_number": 27,
      "audio": {
        "url": "Alafasy/mp3/053038.mp3",
        "segments": [
          [
            0,
            1,
            30,
            790
          ],
          [
            1,
            2,
            800,
            1570
          ],
          [
            2,
            3,
            1580,
            3390
          ],
          [
            3,
            4,
            3400,
            4180
          ],
          [
            4,
            5,
            4190,
            5160
          ]
        ]
      },
      "translations": [
        {
          "id": 662765,
          "resource_id": 101,
          "text": "Ҳеч бир кўтаргувчи (яъни, гуноҳкор жон) ўзга жоннинг юкини (яъни, гуноҳини) кўтармас!"
        }
      ],
      "audio_url": "https://audio.quran.com/reciters/7/Alafasy/mp3/053038.mp3"
    },
    {
      "id": 4823,
      "verse_number": 39,
      "verse_key": "53:39",
      "hizb_number": 53,
      "rub_el_hizb_number": 211,
      "ruku_number": 464,
      "manzil_number": 7,
      "sajdah_number": null,
      "text_uthmani": "وَأَن لَّيْسَ لِلْإِنسَـٰنِ إِلَّا مَا سَعَىٰ",
      "text_uthmani_tajweed": "وَأ<tajweed class=idgham_wo_ghunnah>َن ل</tajweed>َّيْسَ لِلْإِ<tajweed class=ikhafa>نس</tajweed>َ<tajweed class=madda_normal>ـٰ</tajweed>نِ إِلَّا مَا سَعَىٰ <span class=end>٣٩</span>",
      "page_number": 527,
      "juz_number": 27,
      "audio": {
        "url": "Alafasy/mp3/053039.mp3",
        "segments": [
          [
            0,
            1,
            30,
            320
          ],
          [
            1,
            2,
            330,
            1230
          ],
          [
            2,
            3,
            1240,
            3610
          ],
          [
            3,
            4,
            3620,
            4510
          ],
          [
            4,
            5,
            4520,
            4880
          ],
          [
            5,
            6,
            4890,
            5990
          ]
        ]
      },
      "translations": [
        {
          "id": 662766,
          "resource_id": 101,
          "text": "Инсон учун фақат ўзи қилган ҳаракатигина бўлур (яъни, ўзгаларнинг қилган яхши амалларидан унга бирон фойда етмас)."
        }
      ],
      "audio_url": "https://audio.quran.com/reciters/7/Alafasy/mp3/053039.mp3"
    },
    {
      "id": 4824,
      "verse_number": 40,
      "verse_key": "53:40",
      "hizb_number": 53,
      "rub_el_hizb_number": 211,
      "ruku_number": 464,
      "manzil_number": 7,
      "sajdah_number": null,
      "text_uthmani": "وَأَنَّ سَعْيَهُۥ سَوْفَ يُرَىٰ",
      "text_uthmani_tajweed": "وَأَ<tajweed class=ghunnah>نّ</tajweed>َ سَعْيَهُ<tajweed class=madda_normal>ۥ</tajweed> سَوْفَ يُرَىٰ <span class=end>٤٠</span>",
      "page_number": 527,
      "juz_number": 27,
      "audio": {
        "url": "Alafasy/mp3/053040.mp3",
        "segments": [
          [
            0,
            1,
            30,
            1240
          ],
          [
            1,
            2,
            1250,
            2400
          ],
          [
            2,
            3,
            2410,
            3080
          ],
          [
            3,
            4,
            3090,
            4130
          ]
        ]
      },
      "translations": [
        {
          "id": 662767,
          "resource_id": 101,
          "text": "Унинг қилган саъй-ҳаракати эса яқинда (Қиёмат Кунида) кўринур."
        }
      ],
      "audio_url": "https://audio.quran.com/reciters/7/Alafasy/mp3/053040.mp3"
    },
    {
      "id": 4825,
      "verse_number": 41,
      "verse_key": "53:41",
      "hizb_number": 53,
      "rub_el_hizb_number": 211,
      "ruku_number": 464,
      "manzil_number": 7,
      "sajdah_number": null,
      "text_uthmani": "ثُمَّ يُجْزَىٰهُ ٱلْجَزَآءَ ٱلْأَوْفَىٰ",
      "text_uthmani_tajweed": "ثُ<tajweed class=ghunnah>مّ</tajweed>َ يُ<tajweed class=qalaqah>جْ</tajweed>زَ<tajweed class=madda_normal>ٮٰ</tajweed>هُ <tajweed class=ham_wasl>ٱ</tajweed>لْجَز<tajweed class=madda_obligatory>َا</tajweed>ٓءَ <tajweed class=ham_wasl>ٱ</tajweed>لْأَوْفَىٰ <span class=end>٤١</span>",
      "page_number": 527,
      "juz_number": 27,
      "audio": {
        "url": "Alafasy/mp3/053041.mp3",
        "segments": [
          [
            0,
            1,
            30,
            1040
          ],
          [
            1,
            2,
            1050,
            2180
          ],
          [
            2,
            3,
            2190,
            4700
          ],
          [
            3,
            4,
            4710,
            6380
          ]
        ]
      },
      "translations": [
        {
          "id": 662768,
          "resource_id": 101,
          "text": "Сўнгра у (ўша саъй-ҳаракати учун) тўла-тўкис жазо-мукофот олур."
        }
      ],
      "audio_url": "https://audio.quran.com/reciters/7/Alafasy/mp3/053041.mp3"
    },
    {
      "id": 4826,
      "verse_number": 42,
      "verse_key": "53:42",
      "hizb_number": 53,
      "rub_el_hizb_number": 211,
      "ruku_number": 464,
      "manzil_number": 7,
      "sajdah_number": null,
      "text_uthmani": "وَأَنَّ إِلَىٰ رَبِّكَ ٱلْمُنتَهَىٰ",
      "text_uthmani_tajweed": "وَأَ<tajweed class=ghunnah>نّ</tajweed>َ إِلَىٰ رَبِّكَ <tajweed class=ham_wasl>ٱ</tajweed>لْمُ<tajweed class=ikhafa>نت</tajweed>َهَىٰ <span class=end>٤٢</span>",
      "page_number": 527,
      "juz_number": 27,
      "audio": {
        "url": "Alafasy/mp3/053042.mp3",
        "segments": [
          [
            0,
            1,
            30,
            1450
          ],
          [
            1,
            2,
            1460,
            2110
          ],
          [
            2,
            3,
            2120,
            3000
          ],
          [
            3,
            4,
            3010,
            5650
          ]
        ]
      },
      "translations": [
        {
          "id": 662769,
          "resource_id": 101,
          "text": "Албатта охирги чегара ёлғиз Парвардигорингиз олдига (бормоқлик)дир."
        }
      ],
      "audio_url": "https://audio.quran.com/reciters/7/Alafasy/mp3/053042.mp3"
    },
    {
      "id": 4827,
      "verse_number": 43,
      "verse_key": "53:43",
      "hizb_number": 53,
      "rub_el_hizb_number": 211,
      "ruku_number": 464,
      "manzil_number": 7,
      "sajdah_number": null,
      "text_uthmani": "وَأَنَّهُۥ هُوَ أَضْحَكَ وَأَبْكَىٰ",
      "text_uthmani_tajweed": "وَأَ<tajweed class=ghunnah>نّ</tajweed>َهُ<tajweed class=madda_normal>ۥ</tajweed> هُوَ أَضْحَكَ وَأَ<tajweed class=qalaqah>بْ</tajweed>كَىٰ <span class=end>٤٣</span>",
      "page_number": 527,
      "juz_number": 27,
      "audio": {
        "url": "Alafasy/mp3/053043.mp3",
        "segments": [
          [
            0,
            1,
            30,
            1850
          ],
          [
            1,
            2,
            1860,
            2260
          ],
          [
            2,
            3,
            2270,
            3180
          ],
          [
            3,
            4,
            3190,
            4440
          ]
        ]
      },
      "translations": [
        {
          "id": 662770,
          "resource_id": 101,
          "text": "Албатта кулдирган ҳам, йиғлатган ҳам Унинг Ўзидир."
        }
      ],
      "audio_url": "https://audio.quran.com/reciters/7/Alafasy/mp3/053043.mp3"
    },
    {
      "id": 4828,
      "verse_number": 44,
      "verse_key": "53:44",
      "hizb_number": 53,
      "rub_el_hizb_number": 211,
      "ruku_number": 464,
      "manzil_number": 7,
      "sajdah_number": null,
      "text_uthmani": "وَأَنَّهُۥ هُوَ أَمَاتَ وَأَحْيَا",
      "text_uthmani_tajweed": "وَأَ<tajweed class=ghunnah>نّ</tajweed>َهُ<tajweed class=madda_normal>ۥ</tajweed> هُوَ أَمَاتَ وَأَحْيَا <span class=end>٤٤</span>",
      "page_number": 527,
      "juz_number": 27,
      "audio": {
        "url": "Alafasy/mp3/053044.mp3",
        "segments": [
          [
            0,
            1,
            30,
            1900
          ],
          [
            1,
            2,
            1910,
            2280
          ],
          [
            2,
            3,
            2290,
            3240
          ],
          [
            3,
            4,
            3250,
            4490
          ]
        ]
      },
      "translations": [
        {
          "id": 662771,
          "resource_id": 101,
          "text": "Албатта ўлдирган ҳам, тирилтирган ҳам Унинг Ўзидир."
        }
      ],
      "audio_url": "https://audio.quran.com/reciters/7/Alafasy/mp3/053044.mp3"
    },
    {
      "id": 4829,
      "verse_number": 45,
      "verse_key": "53:45",
      "hizb_number": 53,
      "rub_el_hizb_number": 211,
      "ruku_number": 464,
      "manzil_number": 7,
      "sajdah_number": null,
      "text_uthmani": "وَأَنَّهُۥ خَلَقَ ٱلزَّوْجَيْنِ ٱلذَّكَرَ وَٱلْأُنثَىٰ",
      "text_uthmani_tajweed": "وَأَ<tajweed class=ghunnah>نّ</tajweed>َهُ<tajweed class=madda_normal>ۥ</tajweed> خَلَقَ <tajweed class=ham_wasl>ٱ</tajweed><tajweed class=laam_shamsiyah>ل</tajweed>زَّوْجَيْنِ <tajweed class=ham_wasl>ٱ</tajweed><tajweed class=laam_shamsiyah>ل</tajweed>ذَّكَرَ وَ<tajweed class=ham_wasl>ٱ</tajweed>لْأُ<tajweed class=ikhafa>نث</tajweed>َىٰ <span class=end>٤٥</span>",
      "page_number": 528,
      "juz_number": 27,
      "audio": {
        "url": "Alafasy/mp3/053045.mp3",
        "segments": [
          [
            0,
            1,
            30,
            1850
          ],
          [
            1,
            2,
            1860,
            2550
          ],
          [
            2,
            3,
            2560,
            4180
          ],
          [
            3,
            4,
            4190,
            4860
          ],
          [
            4,
            5,
            4870,
            7380
          ]
        ]
      },
      "translations": [
        {
          "id": 662772,
          "resource_id": 101,
          "text": "Ва албатта У зот эркак-аёл жуфтларни яратгандир."
        }
      ],
      "audio_url": "https://audio.quran.com/reciters/7/Alafasy/mp3/053045.mp3"
    },
    {
      "id": 4830,
      "verse_number": 46,
      "verse_key": "53:46",
      "hizb_number": 53,
      "rub_el_hizb_number": 211,
      "ruku_number": 464,
      "manzil_number": 7,
      "sajdah_number": null,
      "text_uthmani": "مِن نُّطْفَةٍ إِذَا تُمْنَىٰ",
      "text_uthmani_tajweed": "م<tajweed class=idgham_ghunnah>ِن ن</tajweed>ُّ<tajweed class=qalaqah>طْ</tajweed>فَةٍ إِذَا تُمْنَىٰ <span class=end>٤٦</span>",
      "page_number": 528,
      "juz_number": 27,
      "audio": {
        "url": "Alafasy/mp3/053046.mp3",
        "segments": [
          [
            0,
            1,
            30,
            980
          ],
          [
            1,
            2,
            990,
            1980
          ],
          [
            2,
            3,
            1990,
            2640
          ],
          [
            3,
            4,
            2650,
            3990
          ]
        ]
      },
      "translations": [
        {
          "id": 662773,
          "resource_id": 101,
          "text": "(Уларни) отилиб чиқадиган нутфадан (яратгандир)."
        }
      ],
      "audio_url": "https://audio.quran.com/reciters/7/Alafasy/mp3/053046.mp3"
    },
    {
      "id": 4831,
      "verse_number": 47,
      "verse_key": "53:47",
      "hizb_number": 53,
      "rub_el_hizb_number": 211,
      "ruku_number": 464,
      "manzil_number": 7,
      "sajdah_number": null,
      "text_uthmani": "وَأَنَّ عَلَيْهِ ٱلنَّشْأَةَ ٱلْأُخْرَىٰ",
      "text_uthmani_tajweed": "وَأَ<tajweed class=ghunnah>نّ</tajweed>َ عَلَيْهِ <tajweed class=ham_wasl>ٱ</tajweed><tajweed class=laam_shamsiyah>ل</tajweed><tajweed class=ghunnah>نّ</tajweed>َشْأَةَ <tajweed class=ham_wasl>ٱ</tajweed>لْأُخْرَىٰ <span class=end>٤٧</span>",
      "page_number": 528,
      "juz_number": 27,
      "audio": {
        "url": "Alafasy/mp3/053047.mp3",
        "segments": [
          [
            0,
            1,
            30,
            1270
          ],
          [
            1,
            2,
            1280,
            2330
          ],
          [
            2,
            3,
            2340,
            4000
          ],
          [
            3,
            4,
            4010,
            5420
          ]
        ]
      },
      "translations": [
        {
          "id": 662774,
          "resource_id": 101,
          "text": "Албатта (барча халойиқни ўлганидан сўнг) иккинчи бор пайдо қилиш ҳам ёлғиз Унинг зиммасидадир."
        }
      ],
      "audio_url": "https://audio.quran.com/reciters/7/Alafasy/mp3/053047.mp3"
    },
    {
      "id": 4832,
      "verse_number": 48,
      "verse_key": "53:48",
      "hizb_number": 53,
      "rub_el_hizb_number": 211,
      "ruku_number": 464,
      "manzil_number": 7,
      "sajdah_number": null,
      "text_uthmani": "وَأَنَّهُۥ هُوَ أَغْنَىٰ وَأَقْنَىٰ",
      "text_uthmani_tajweed": "وَأَ<tajweed class=ghunnah>نّ</tajweed>َهُ<tajweed class=madda_normal>ۥ</tajweed> هُوَ أَغْنَىٰ وَأَ<tajweed class=qalaqah>قْ</tajweed>نَىٰ <span class=end>٤٨</span>",
      "page_number": 528,
      "juz_number": 27,
      "audio": {
        "url": "Alafasy/mp3/053048.mp3",
        "segments": [
          [
            0,
            1,
            30,
            2100
          ],
          [
            1,
            2,
            2110,
            2510
          ],
          [
            2,
            3,
            2520,
            3430
          ],
          [
            3,
            4,
            3440,
            4750
          ]
        ]
      },
      "translations": [
        {
          "id": 662775,
          "resource_id": 101,
          "text": "Албатта бой қилган ҳам, бадавлат қилган ҳам Унинг Ўзидир."
        }
      ],
      "audio_url": "https://audio.quran.com/reciters/7/Alafasy/mp3/053048.mp3"
    },
    {
      "id": 4833,
      "verse_number": 49,
      "verse_key": "53:49",
      "hizb_number": 53,
      "rub_el_hizb_number": 211,
      "ruku_number": 464,
      "manzil_number": 7,
      "sajdah_number": null,
      "text_uthmani": "وَأَنَّهُۥ هُوَ رَبُّ ٱلشِّعْرَىٰ",
      "text_uthmani_tajweed": "وَأَ<tajweed class=ghunnah>نّ</tajweed>َهُ<tajweed class=madda_normal>ۥ</tajweed> هُوَ رَبُّ <tajweed class=ham_wasl>ٱ</tajweed><tajweed class=laam_shamsiyah>ل</tajweed>شِّعْرَىٰ <span class=end>٤٩</span>",
      "page_number": 528,
      "juz_number": 27,
      "audio": {
        "url": "Alafasy/mp3/053049.mp3",
        "segments": [
          [
            0,
            1,
            30,
            1700
          ],
          [
            1,
            2,
            1710,
            2170
          ],
          [
            2,
            3,
            2180,
            2800
          ],
          [
            3,
            4,
            2810,
            4070
          ]
        ]
      },
      "translations": [
        {
          "id": 662776,
          "resource_id": 101,
          "text": "Албатта Шеъро (юлдузи)нинг Парвардигори ҳам Унинг Ўзидир. <sup foot_note=145273>1</sup>"
        }
      ],
      "audio_url": "https://audio.quran.com/reciters/7/Alafasy/mp3/053049.mp3"
    },
    {
      "id": 4834,
      "verse_number": 50,
      "verse_key": "53:50",
      "hizb_number": 53,
      "rub_el_hizb_number": 211,
      "ruku_number": 464,
      "manzil_number": 7,
      "sajdah_number": null,
      "text_uthmani": "وَأَنَّهُۥٓ أَهْلَكَ عَادًا ٱلْأُولَىٰ",
      "text_uthmani_tajweed": "وَأَ<tajweed class=ghunnah>نّ</tajweed>َهُ<tajweed class=madda_obligatory>ۥٓ</tajweed> أَهْلَكَ عَادًا <tajweed class=ham_wasl>ٱ</tajweed>لْأُولَىٰ <span class=end>٥٠</span>",
      "page_number": 528,
      "juz_number": 27,
      "audio": {
        "url": "Alafasy/mp3/053050.mp3",
        "segments": [
          [
            0,
            1,
            30,
            2940
          ],
          [
            1,
            2,
            2950,
            3760
          ],
          [
            2,
            3,
            3770,
            4550
          ],
          [
            3,
            4,
            4560,
            5890
          ]
        ]
      },
      "translations": [
        {
          "id": 662777,
          "resource_id": 101,
          "text": "Албатта У зот аввалги Од (қабиласи)ни ҳалок қилди;"
        }
      ],
      "audio_url": "https://audio.quran.com/reciters/7/Alafasy/mp3/053050.mp3"
    },
    {
      "id": 4835,
      "verse_number": 51,
      "verse_key": "53:51",
      "hizb_number": 53,
      "rub_el_hizb_number": 211,
      "ruku_number": 464,
      "manzil_number": 7,
      "sajdah_number": null,
      "text_uthmani": "وَثَمُودَا۟ فَمَآ أَبْقَىٰ",
      "text_uthmani_tajweed": "وَثَمُودَ<tajweed class=slnt>اْ</tajweed> فَم<tajweed class=madda_obligatory>َآ</tajweed> أَ<tajweed class=qalaqah>بْ</tajweed>قَىٰ <span class=end>٥١</span>",
      "page_number": 528,
      "juz_number": 27,
      "audio": {
        "url": "Alafasy/mp3/053051.mp3",
        "segments": [
          [
            0,
            1,
            30,
            1090
          ],
          [
            1,
            2,
            1100,
            3440
          ],
          [
            2,
            3,
            3450,
            4450
          ]
        ]
      },
      "translations": [
        {
          "id": 662778,
          "resource_id": 101,
          "text": "Ва Самуд (қабиласи)ни ҳам (ҳалок қилди), бас (улардан бирон кишини тирик) қолдирмади."
        }
      ],
      "audio_url": "https://audio.quran.com/reciters/7/Alafasy/mp3/053051.mp3"
    },
    {
      "id": 4836,
      "verse_number": 52,
      "verse_key": "53:52",
      "hizb_number": 53,
      "rub_el_hizb_number": 211,
      "ruku_number": 464,
      "manzil_number": 7,
      "sajdah_number": null,
      "text_uthmani": "وَقَوْمَ نُوحٍ مِّن قَبْلُ ۖ إِنَّهُمْ كَانُوا۟ هُمْ أَظْلَمَ وَأَطْغَىٰ",
      "text_uthmani_tajweed": "وَقَوْمَ نُو<tajweed class=idgham_ghunnah>حٍ م</tajweed>ِّ<tajweed class=ikhafa>ن ق</tajweed>َ<tajweed class=qalaqah>بْ</tajweed>لُ‌ۖ إِ<tajweed class=ghunnah>نّ</tajweed>َهُمْ كَانُو<tajweed class=slnt>اْ</tajweed> هُمْ أَظْلَمَ وَأَ<tajweed class=qalaqah>طْ</tajweed>غَىٰ <span class=end>٥٢</span>",
      "page_number": 528,
      "juz_number": 27,
      "audio": {
        "url": "Alafasy/mp3/053052.mp3",
        "segments": [
          [
            0,
            1,
            30,
            840
          ],
          [
            1,
            2,
            850,
            2430
          ],
          [
            2,
            3,
            2440,
            3780
          ],
          [
            3,
            4,
            3790,
            4770
          ],
          [
            4,
            5,
            4780,
            6610
          ],
          [
            5,
            6,
            6620,
            7560
          ],
          [
            6,
            7,
            7570,
            8020
          ],
          [
            7,
            8,
            8030,
            8920
          ],
          [
            8,
            9,
            8930,
            10260
          ]
        ]
      },
      "translations": [
        {
          "id": 662779,
          "resource_id": 101,
          "text": "Яна У зот илгари Нуҳ қавмини ҳам (ҳалок қилгандир). Чунки уларнинг ўзлари жуда золим ва туғёнга тушган кимсалар эдилар."
        }
      ],
      "audio_url": "https://audio.quran.com/reciters/7/Alafasy/mp3/053052.mp3"
    },
    {
      "id": 4837,
      "verse_number": 53,
      "verse_key": "53:53",
      "hizb_number": 53,
      "rub_el_hizb_number": 211,
      "ruku_number": 464,
      "manzil_number": 7,
      "sajdah_number": null,
      "text_uthmani": "وَٱلْمُؤْتَفِكَةَ أَهْوَىٰ",
      "text_uthmani_tajweed": "وَ<tajweed class=ham_wasl>ٱ</tajweed>لْمُؤْتَفِكَةَ أَهْوَىٰ <span class=end>٥٣</span>",
      "page_number": 528,
      "juz_number": 27,
      "audio": {
        "url": "Alafasy/mp3/053053.mp3",
        "segments": [
          [
            0,
            1,
            30,
            1790
          ],
          [
            1,
            2,
            1800,
            3150
          ]
        ]
      },
      "translations": [
        {
          "id": 662780,
          "resource_id": 101,
          "text": "Яна У зот зеру-забар бўлган қишлоқни (яъни, Лут пайғамбар қавмини) ҳам қулатиб,"
        }
      ],
      "audio_url": "https://audio.quran.com/reciters/7/Alafasy/mp3/053053.mp3"
    },
    {
      "id": 4838,
      "verse_number": 54,
      "verse_key": "53:54",
      "hizb_number": 53,
      "rub_el_hizb_number": 211,
      "ruku_number": 464,
      "manzil_number": 7,
      "sajdah_number": null,
      "text_uthmani": "فَغَشَّىٰهَا مَا غَشَّىٰ",
      "text_uthmani_tajweed": "فَغَشَّ<tajweed class=madda_normal>ـٰ</tajweed>هَا مَا غَشَّىٰ <span class=end>٥٤</span>",
      "page_number": 528,
      "juz_number": 27,
      "audio": {
        "url": "Alafasy/mp3/053054.mp3",
        "segments": [
          [
            0,
            1,
            30,
            1530
          ],
          [
            1,
            2,
            1540,
            1940
          ],
          [
            2,
            3,
            1950,
            3220
          ]
        ]
      },
      "translations": [
        {
          "id": 662781,
          "resource_id": 101,
          "text": "уни ўраган нарса (яъни, осмонда ёғилган тошлар) билан ўраб кўмиб ташлади."
        }
      ],
      "audio_url": "https://audio.quran.com/reciters/7/Alafasy/mp3/053054.mp3"
    },
    {
      "id": 4839,
      "verse_number": 55,
      "verse_key": "53:55",
      "hizb_number": 53,
      "rub_el_hizb_number": 211,
      "ruku_number": 464,
      "manzil_number": 7,
      "sajdah_number": null,
      "text_uthmani": "فَبِأَىِّ ءَالَآءِ رَبِّكَ تَتَمَارَىٰ",
      "text_uthmani_tajweed": "فَبِأَىِّ ءَال<tajweed class=madda_obligatory>َا</tajweed>ٓءِ رَبِّكَ تَتَمَارَىٰ <span class=end>٥٥</span>",
      "page_number": 528,
      "juz_number": 27,
      "audio": {
        "url": "Alafasy/mp3/053055.mp3",
        "segments": [
          [
            0,
            1,
            30,
            1110
          ],
          [
            1,
            2,
            1120,
            3460
          ],
          [
            2,
            3,
            3470,
            4330
          ],
          [
            3,
            4,
            4340,
            6080
          ]
        ]
      },
      "translations": [
        {
          "id": 662782,
          "resource_id": 101,
          "text": "Бас, (эй инсон) Парвардигорингнинг қайси неъматлари ҳақида шак-шубҳа қилурсан?!"
        }
      ],
      "audio_url": "https://audio.quran.com/reciters/7/Alafasy/mp3/053055.mp3"
    },
    {
      "id": 4840,
      "verse_number": 56,
      "verse_key": "53:56",
      "hizb_number": 53,
      "rub_el_hizb_number": 211,
      "ruku_number": 464,
      "manzil_number": 7,
      "sajdah_number": null,
      "text_uthmani": "هَـٰذَا نَذِيرٌ مِّنَ ٱلنُّذُرِ ٱلْأُولَىٰٓ",
      "text_uthmani_tajweed": "هَ<tajweed class=madda_normal>ـٰ</tajweed>ذَا نَذِي<tajweed class=idgham_ghunnah>رٌ م</tajweed>ِّنَ <tajweed class=ham_wasl>ٱ</tajweed><tajweed class=laam_shamsiyah>ل</tajweed><tajweed class=ghunnah>نّ</tajweed>ُذُرِ <tajweed class=ham_wasl>ٱ</tajweed>لْأُولَىٰٓ <span class=end>٥٦</span>",
      "page_number": 528,
      "juz_number": 27,
      "audio": {
        "url": "Alafasy/mp3/053056.mp3",
        "segments": [
          [
            0,
            1,
            30,
            890
          ],
          [
            1,
            2,
            900,
            2680
          ],
          [
            2,
            3,
            2690,
            3640
          ],
          [
            3,
            4,
            3650,
            4700
          ],
          [
            4,
            5,
            4710,
            6170
          ]
        ]
      },
      "translations": [
        {
          "id": 662783,
          "resource_id": 101,
          "text": "Бу (яъни, Муҳаммад алайҳис-салоту вас-салом ҳам) аввалги огоҳлантиргувчилар (пайғамбарлар жумласи)дан бир огоҳлантиргувчидир."
        }
      ],
      "audio_url": "https://audio.quran.com/reciters/7/Alafasy/mp3/053056.mp3"
    },
    {
      "id": 4841,
      "verse_number": 57,
      "verse_key": "53:57",
      "hizb_number": 53,
      "rub_el_hizb_number": 211,
      "ruku_number": 464,
      "manzil_number": 7,
      "sajdah_number": null,
      "text_uthmani": "أَزِفَتِ ٱلْـَٔازِفَةُ",
      "text_uthmani_tajweed": "أَزِفَتِ <tajweed class=ham_wasl>ٱ</tajweed>لْأَزِفَةُ <span class=end>٥٧</span>",
      "page_number": 528,
      "juz_number": 27,
      "audio": {
        "url": "Alafasy/mp3/053057.mp3",
        "segments": [
          [
            0,
            1,
            30,
            840
          ],
          [
            1,
            2,
            850,
            2070
          ]
        ]
      },
      "translations": [
        {
          "id": 662784,
          "resource_id": 101,
          "text": "Яқин бўлгувчи (Қиёмат) яқин қолди."
        }
      ],
      "audio_url": "https://audio.quran.com/reciters/7/Alafasy/mp3/053057.mp3"
    },
    {
      "id": 4842,
      "verse_number": 58,
      "verse_key": "53:58",
      "hizb_number": 53,
      "rub_el_hizb_number": 211,
      "ruku_number": 464,
      "manzil_number": 7,
      "sajdah_number": null,
      "text_uthmani": "لَيْسَ لَهَا مِن دُونِ ٱللَّهِ كَاشِفَةٌ",
      "text_uthmani_tajweed": "لَيْسَ لَهَا مِ<tajweed class=ikhafa>ن د</tajweed>ُونِ <tajweed class=ham_wasl>ٱ</tajweed>للَّهِ كَاشِفَةٌ <span class=end>٥٨</span>",
      "page_number": 528,
      "juz_number": 27,
      "audio": {
        "url": "Alafasy/mp3/053058.mp3",
        "segments": [
          [
            0,
            1,
            30,
            680
          ],
          [
            1,
            2,
            690,
            1370
          ],
          [
            2,
            3,
            1380,
            2680
          ],
          [
            3,
            4,
            2690,
            3430
          ],
          [
            4,
            5,
            3440,
            4290
          ],
          [
            5,
            6,
            4300,
            5400
          ]
        ]
      },
      "translations": [
        {
          "id": 662785,
          "resource_id": 101,
          "text": "Унинг учун Аллоҳдан ўзга бирон очгувчи (қачон бўлишини билдиргувчи) йўқдир."
        }
      ],
      "audio_url": "https://audio.quran.com/reciters/7/Alafasy/mp3/053058.mp3"
    },
    {
      "id": 4843,
      "verse_number": 59,
      "verse_key": "53:59",
      "hizb_number": 53,
      "rub_el_hizb_number": 211,
      "ruku_number": 464,
      "manzil_number": 7,
      "sajdah_number": null,
      "text_uthmani": "أَفَمِنْ هَـٰذَا ٱلْحَدِيثِ تَعْجَبُونَ",
      "text_uthmani_tajweed": "أَفَمِنْ هَ<tajweed class=madda_normal>ـٰ</tajweed>ذَا <tajweed class=ham_wasl>ٱ</tajweed>لْحَدِيثِ تَعْجَب<tajweed class=madda_permissible>ُو</tajweed>نَ <span class=end>٥٩</span>",
      "page_number": 528,
      "juz_number": 27,
      "audio": {
        "url": "Alafasy/mp3/053059.mp3",
        "segments": [
          [
            0,
            1,
            30,
            790
          ],
          [
            1,
            2,
            800,
            1490
          ],
          [
            2,
            3,
            1500,
            2650
          ],
          [
            3,
            4,
            2660,
            5610
          ]
        ]
      },
      "translations": [
        {
          "id": 662786,
          "resource_id": 101,
          "text": "(Эй мушриклар), ҳали сизлар мана шу Сўздан (Қуръондан) ажабланурсизларми?!"
        }
      ],
      "audio_url": "https://audio.quran.com/reciters/7/Alafasy/mp3/053059.mp3"
    },
    {
      "id": 4844,
      "verse_number": 60,
      "verse_key": "53:60",
      "hizb_number": 53,
      "rub_el_hizb_number": 211,
      "ruku_number": 464,
      "manzil_number": 7,
      "sajdah_number": null,
      "text_uthmani": "وَتَضْحَكُونَ وَلَا تَبْكُونَ",
      "text_uthmani_tajweed": "وَتَضْحَكُونَ وَلَا تَ<tajweed class=qalaqah>بْ</tajweed>ك<tajweed class=madda_permissible>ُو</tajweed>نَ <span class=end>٦٠</span>",
      "page_number": 528,
      "juz_number": 27,
      "audio": {
        "url": "Alafasy/mp3/053060.mp3",
        "segments": [
          [
            0,
            1,
            30,
            1600
          ],
          [
            1,
            2,
            1610,
            2240
          ],
          [
            2,
            3,
            2250,
            5330
          ]
        ]
      },
      "translations": [
        {
          "id": 662787,
          "resource_id": 101,
          "text": "(Ундаги оятларнинг беназир ва бемисл ўгит-насиҳатларидан таъсирланиб) йиғламасдан, кулурсизларми?"
        }
      ],
      "audio_url": "https://audio.quran.com/reciters/7/Alafasy/mp3/053060.mp3"
    },
    {
      "id": 4845,
      "verse_number": 61,
      "verse_key": "53:61",
      "hizb_number": 53,
      "rub_el_hizb_number": 211,
      "ruku_number": 464,
      "manzil_number": 7,
      "sajdah_number": null,
      "text_uthmani": "وَأَنتُمْ سَـٰمِدُونَ",
      "text_uthmani_tajweed": "وَأَ<tajweed class=ikhafa>نت</tajweed>ُمْ سَ<tajweed class=madda_normal>ـٰ</tajweed>مِد<tajweed class=madda_permissible>ُو</tajweed>نَ <span class=end>٦١</span>",
      "page_number": 528,
      "juz_number": 27,
      "audio": {
        "url": "Alafasy/mp3/053061.mp3",
        "segments": [
          [
            0,
            1,
            30,
            2060
          ],
          [
            1,
            2,
            2070,
            5650
          ]
        ]
      },
      "translations": [
        {
          "id": 662788,
          "resource_id": 101,
          "text": "Ғофил бўлган ҳолларингизда (йиғламасдан, кулурсизларми?!)"
        }
      ],
      "audio_url": "https://audio.quran.com/reciters/7/Alafasy/mp3/053061.mp3"
    },
    {
      "id": 4846,
      "verse_number": 62,
      "verse_key": "53:62",
      "hizb_number": 53,
      "rub_el_hizb_number": 211,
      "ruku_number": 464,
      "manzil_number": 7,
      "sajdah_number": 12,
      "text_uthmani": "فَٱسْجُدُوا۟ لِلَّهِ وَٱعْبُدُوا۟ ۩",
      "text_uthmani_tajweed": "فَ<tajweed class=ham_wasl>ٱ</tajweed>سْجُدُو<tajweed class=slnt>اْ</tajweed> لِلَّهِ وَ<tajweed class=ham_wasl>ٱ</tajweed>عْبُدُو<tajweed class=slnt>اْ</tajweed> ۩ <span class=end>٦٢</span>",
      "page_number": 528,
      "juz_number": 27,
      "audio": {
        "url": "Alafasy/mp3/053062.mp3",
        "segments": [
          [
            0,
            1,
            30,
            1170
          ],
          [
            1,
            2,
            1180,
            2390
          ],
          [
            2,
            3,
            2400,
            3700
          ]
        ]
      },
      "translations": [
        {
          "id": 662789,
          "resource_id": 101,
          "text": "Бас, сизлар ёлғиз Аллоҳга сажда ва ибодат қилинглар! <sup foot_note=145274>1</sup>"
        }
      ],
      "audio_url": "https://audio.quran.com/reciters/7/Alafasy/mp3/053062.mp3"
    }
  ]
}
